[{"played_battles": 21, "won_battles": 18, "lost_battles": 3, "draw_battles": 0, "win_rate": "86 %", "points_earned": "12179", "wlr": "6.00", "player_level": "73073", "battles_history": [{"result": "Defeat", "won_rounds": 2, "played_rounds": 5, "raw_points": "732", "beating_factor": "0.40", "won_points": "293", "event": "SSLT 1", "video": "https://www.youtube.com/watch?v=Rm77d1E42fQ", "rival": "raynarrok"}, {"result": "Victory", "won_rounds": 3, "played_rounds": 3, "raw_points": "720", "beating_factor": "1.00", "won_points": "720", "event": "SSLT 1", "video": "https://www.youtube.com/watch?v=Rm77d1E42fQ", "rival": "raynarrok"}, {"result": "Victory", "won_rounds": 3, "played_rounds": 4, "raw_points": "888", "beating_factor": "0.75", "won_points": "666", "event": "SSLT 1", "video": "https://www.youtube.com/watch?v=Rm77d1E42fQ", "rival": "raynarrok"}, {"result": "Victory", "won_rounds": 3, "played_rounds": 4, "raw_points": "888", "beating_factor": "0.75", "won_points": "666", "event": "SSLT 1", "video": "https://www.youtube.com/watch?v=C2mgUuDnLaI", "rival": "Kovas"}, {"result": "Victory", "won_rounds": 3, "played_rounds": 3, "raw_points": "720", "beating_factor": "1.00", "won_points": "720", "event": "SSLT 1", "video": "https://www.youtube.com/watch?v=C2mgUuDnLaI", "rival": "Kovas"}, {"result": "Victory", "won_rounds": 3, "played_rounds": 3, "raw_points": "720", "beating_factor": "1.00", "won_points": "720", "event": "SSLT 1", "video": "https://www.youtube.com/watch?v=C2mgUuDnLaI", "rival": "Kovas"}, {"result": "Defeat", "won_rounds": 1, "played_rounds": 4, "raw_points": "576", "beating_factor": "0.25", "won_points": "144", "event": "SSLT 1", "video": "https://www.youtube.com/watch?v=QrzOcS2Fseg", "rival": "raynarrok"}, {"result": "Victory", "won_rounds": 3, "played_rounds": 3, "raw_points": "720", "beating_factor": "1.00", "won_points": "720", "event": "SSLT 1", "video": "https://www.youtube.com/watch?v=QrzOcS2Fseg", "rival": "raynarrok"}, {"result": "Victory", "won_rounds": 3, "played_rounds": 3, "raw_points": "720", "beating_factor": "1.00", "won_points": "720", "event": "SSLT 1", "video": "https://www.youtube.com/watch?v=QrzOcS2Fseg", "rival": "raynarrok"}, {"result": "Victory", "won_rounds": 3, "played_rounds": 3, "raw_points": "720", "beating_factor": "1.00", "won_points": "720", "event": "SSLT 1", "video": "https://www.youtube.com/watch?v=QrzOcS2Fseg", "rival": "raynarrok"}, {"result": "Defeat", "won_rounds": 2, "played_rounds": 5, "raw_points": "816", "beating_factor": "0.40", "won_points": "326", "event": "SSLT 3", "video": "https://www.youtube.com/watch?v=8y18kruwQV0", "rival": "Eche"}, {"result": "Victory", "won_rounds": 3, "played_rounds": 5, "raw_points": "888", "beating_factor": "0.60", "won_points": "533", "event": "SSLT 3", "video": "https://www.youtube.com/watch?v=8y18kruwQV0", "rival": "Eche"}, {"result": "Victory", "won_rounds": 3, "played_rounds": 5, "raw_points": "972", "beating_factor": "0.60", "won_points": "583", "event": "SSLT 3", "video": "https://www.youtube.com/watch?v=8y18kruwQV0", "rival": "Eche"}, {"result": "Victory", "won_rounds": 3, "played_rounds": 4, "raw_points": "804", "beating_factor": "0.75", "won_points": "603", "event": "SSLT 3", "video": "https://www.youtube.com/watch?v=z1RFr37KAeE", "rival": "JaffarWolf"}, {"result": "Victory", "won_rounds": 3, "played_rounds": 4, "raw_points": "804", "beating_factor": "0.75", "won_points": "603", "event": "SSLT 3", "video": "https://www.youtube.com/watch?v=z1RFr37KAeE", "rival": "JaffarWolf"}, {"result": "Victory", "won_rounds": 3, "played_rounds": 5, "raw_points": "888", "beating_factor": "0.60", "won_points": "533", "event": "SSLT 3", "video": "https://www.youtube.com/watch?v=vl_mNMwesos", "rival": "zen-x"}, {"result": "Victory", "won_rounds": 3, "played_rounds": 5, "raw_points": "888", "beating_factor": "0.60", "won_points": "533", "event": "SSLT 3", "video": "https://www.youtube.com/watch?v=vl_mNMwesos", "rival": "zen-x"}, {"result": "Victory", "won_rounds": 3, "played_rounds": 5, "raw_points": "972", "beating_factor": "0.60", "won_points": "583", "event": "SSLT 3", "video": "https://www.youtube.com/watch?v=vl_mNMwesos", "rival": "zen-x"}, {"result": "Victory", "won_rounds": 3, "played_rounds": 3, "raw_points": "720", "beating_factor": "1.00", "won_points": "720", "event": "SSLT 3", "video": "https://www.youtube.com/watch?v=bFys_Gvfb4U", "rival": "raynarrok"}, {"result": "Victory", "won_rounds": 3, "played_rounds": 5, "raw_points": "888", "beating_factor": "0.60", "won_points": "533", "event": "SSLT 3", "video": "https://www.youtube.com/watch?v=bFys_Gvfb4U", "rival": "raynarrok"}, {"result": "Victory", "won_rounds": 3, "played_rounds": 4, "raw_points": "720", "beating_factor": "0.75", "won_points": "540", "event": "SSLT 3", "video": "https://www.youtube.com/watch?v=bFys_Gvfb4U", "rival": "raynarrok"}], "player": "wylde"}, {"played_battles": 24, "won_battles": 20, "lost_battles": 4, "draw_battles": 0, "win_rate": "83 %", "points_earned": "14100", "wlr": "5.00", "player_level": "70500", "battles_history": [{"result": "Victory", "won_rounds": 3, "played_rounds": 4, "raw_points": "804", "beating_factor": "0.75", "won_points": "603", "event": "SSLT 4", "video": "https://www.youtube.com/watch?v=K_B5jRkZsAg", "rival": "LN Mastodon"}, {"result": "Victory", "won_rounds": 3, "played_rounds": 3, "raw_points": "720", "beating_factor": "1.00", "won_points": "720", "event": "SSLT 4", "video": "https://www.youtube.com/watch?v=K_B5jRkZsAg", "rival": "LN Mastodon"}, {"result": "Victory", "won_rounds": 3, "played_rounds": 5, "raw_points": "972", "beating_factor": "0.60", "won_points": "583", "event": "SSLT 4", "video": "https://www.youtube.com/watch?v=qqKkNZU-R7Q", "rival": "Kyorage"}, {"result": "Victory", "won_rounds": 3, "played_rounds": 5, "raw_points": "972", "beating_factor": "0.60", "won_points": "583", "event": "SSLT 4", "video": "https://www.youtube.com/watch?v=qqKkNZU-R7Q", "rival": "Kyorage"}, {"result": "Victory", "won_rounds": 3, "played_rounds": 4, "raw_points": "888", "beating_factor": "0.75", "won_points": "666", "event": "SSLT 4", "video": "https://www.youtube.com/watch?v=A0EVqbG_56g", "rival": "Gontranno"}, {"result": "Victory", "won_rounds": 3, "played_rounds": 5, "raw_points": "1056", "beating_factor": "0.60", "won_points": "634", "event": "SSLT 4", "video": "https://www.youtube.com/watch?v=A0EVqbG_56g", "rival": "Gontranno"}, {"result": "Defeat", "won_rounds": 1, "played_rounds": 4, "raw_points": "744", "beating_factor": "0.25", "won_points": "186", "event": "SSLT 4", "video": "https://www.youtube.com/watch?v=A0EVqbG_56g", "rival": "Gontranno"}, {"result": "Defeat", "won_rounds": 2, "played_rounds": 5, "raw_points": "816", "beating_factor": "0.40", "won_points": "326", "event": "SSLT 4", "video": "https://www.youtube.com/watch?v=A0EVqbG_56g", "rival": "Gontranno"}, {"result": "Victory", "won_rounds": 3, "played_rounds": 3, "raw_points": "720", "beating_factor": "1.00", "won_points": "720", "event": "SSLT 4", "video": "https://www.youtube.com/watch?v=A0EVqbG_56g", "rival": "Gontranno"}, {"result": "Victory", "won_rounds": 3, "played_rounds": 4, "raw_points": "804", "beating_factor": "0.75", "won_points": "603", "event": "SSLT 4", "video": "https://www.youtube.com/watch?v=a73720BuEY4", "rival": "Kyorage"}, {"result": "Victory", "won_rounds": 3, "played_rounds": 3, "raw_points": "720", "beating_factor": "1.00", "won_points": "720", "event": "SSLT 4", "video": "https://www.youtube.com/watch?v=a73720BuEY4", "rival": "Kyorage"}, {"result": "Victory", "won_rounds": 3, "played_rounds": 3, "raw_points": "720", "beating_factor": "1.00", "won_points": "720", "event": "SSLT 4", "video": "https://www.youtube.com/watch?v=a73720BuEY4", "rival": "Kyorage"}, {"result": "Victory", "won_rounds": 3, "played_rounds": 3, "raw_points": "720", "beating_factor": "1.00", "won_points": "720", "event": "SSLT 6", "video": "https://youtu.be/aYMnPaA4Ydk", "rival": "Junixart"}, {"result": "Victory", "won_rounds": 3, "played_rounds": 3, "raw_points": "720", "beating_factor": "1.00", "won_points": "720", "event": "SSLT 6", "video": "https://youtu.be/aYMnPaA4Ydk", "rival": "Junixart"}, {"result": "Victory", "won_rounds": 3, "played_rounds": 3, "raw_points": "720", "beating_factor": "1.00", "won_points": "720", "event": "SSLT 6", "video": "https://youtu.be/tISgzPQCl4w", "rival": "Sebas"}, {"result": "Victory", "won_rounds": 3, "played_rounds": 4, "raw_points": "888", "beating_factor": "0.75", "won_points": "666", "event": "SSLT 6", "video": "https://youtu.be/tISgzPQCl4w", "rival": "Sebas"}, {"result": "Victory", "won_rounds": 3, "played_rounds": 5, "raw_points": "972", "beating_factor": "0.60", "won_points": "583", "event": "SSLT 6", "video": "https://youtu.be/P_trs_RNRx8", "rival": "Karol"}, {"result": "Defeat", "won_rounds": 2, "played_rounds": 5, "raw_points": "816", "beating_factor": "0.40", "won_points": "326", "event": "SSLT 6", "video": "https://youtu.be/P_trs_RNRx8", "rival": "Karol"}, {"result": "Victory", "won_rounds": 3, "played_rounds": 4, "raw_points": "804", "beating_factor": "0.75", "won_points": "603", "event": "SSLT 6", "video": "https://youtu.be/P_trs_RNRx8", "rival": "Karol"}, {"result": "Defeat", "won_rounds": 0, "played_rounds": 3, "raw_points": "420", "beating_factor": "0.10", "won_points": "42", "event": "SSLT 6", "video": "https://youtu.be/P_trs_RNRx8", "rival": "Karol"}, {"result": "Victory", "won_rounds": 3, "played_rounds": 4, "raw_points": "888", "beating_factor": "0.75", "won_points": "666", "event": "SSLT 6", "video": "https://youtu.be/P_trs_RNRx8", "rival": "Karol"}, {"result": "Victory", "won_rounds": 3, "played_rounds": 4, "raw_points": "888", "beating_factor": "0.75", "won_points": "666", "event": "SSLT 6", "video": "https://youtu.be/fi6gL2gjBFI", "rival": "Junixart"}, {"result": "Victory", "won_rounds": 3, "played_rounds": 4, "raw_points": "804", "beating_factor": "0.75", "won_points": "603", "event": "SSLT 6", "video": "https://youtu.be/fi6gL2gjBFI", "rival": "Junixart"}, {"result": "Victory", "won_rounds": 3, "played_rounds": 3, "raw_points": "720", "beating_factor": "1.00", "won_points": "720", "event": "SSLT 6", "video": "https://youtu.be/fi6gL2gjBFI", "rival": "Junixart"}], "player": "Lang"}, {"played_battles": 11, "won_battles": 10, "lost_battles": 1, "draw_battles": 0, "win_rate": "91 %", "points_earned": "6801", "wlr": "10.00", "player_level": "68010", "battles_history": [{"result": "Victory", "won_rounds": 3, "played_rounds": 4, "raw_points": "888", "beating_factor": "0.75", "won_points": "666", "event": "SSLT 5", "video": "https://www.youtube.com/watch?v=eIoutvA67tM", "rival": "Megarl"}, {"result": "Victory", "won_rounds": 3, "played_rounds": 3, "raw_points": "720", "beating_factor": "1.00", "won_points": "720", "event": "SSLT 5", "video": "https://www.youtube.com/watch?v=eIoutvA67tM", "rival": "Megarl"}, {"result": "Victory", "won_rounds": 3, "played_rounds": 4, "raw_points": "720", "beating_factor": "0.75", "won_points": "540", "event": "SSLT 5", "video": "https://www.youtube.com/watch?v=XIHIgK0bGVU", "rival": "JaffarWolf"}, {"result": "Victory", "won_rounds": 3, "played_rounds": 3, "raw_points": "720", "beating_factor": "1.00", "won_points": "720", "event": "SSLT 5", "video": "https://www.youtube.com/watch?v=XIHIgK0bGVU", "rival": "JaffarWolf"}, {"result": "Victory", "won_rounds": 3, "played_rounds": 4, "raw_points": "804", "beating_factor": "0.75", "won_points": "603", "event": "SSLT 5", "video": "https://www.youtube.com/watch?v=2K5L_cYr39M", "rival": "zen-x"}, {"result": "Victory", "won_rounds": 3, "played_rounds": 3, "raw_points": "720", "beating_factor": "1.00", "won_points": "720", "event": "SSLT 5", "video": "https://www.youtube.com/watch?v=2K5L_cYr39M", "rival": "zen-x"}, {"result": "Victory", "won_rounds": 3, "played_rounds": 3, "raw_points": "720", "beating_factor": "1.00", "won_points": "720", "event": "SSLT 5", "video": "https://www.youtube.com/watch?v=2K5L_cYr39M", "rival": "zen-x"}, {"result": "Victory", "won_rounds": 3, "played_rounds": 4, "raw_points": "888", "beating_factor": "0.75", "won_points": "666", "event": "SSLT 5", "video": "https://www.youtube.com/watch?v=cgNvghyR3BA", "rival": "Fire Red"}, {"result": "Defeat", "won_rounds": 1, "played_rounds": 4, "raw_points": "492", "beating_factor": "0.25", "won_points": "123", "event": "SSLT 5", "video": "https://www.youtube.com/watch?v=cgNvghyR3BA", "rival": "Fire Red"}, {"result": "Victory", "won_rounds": 3, "played_rounds": 3, "raw_points": "720", "beating_factor": "1.00", "won_points": "720", "event": "SSLT 5", "video": "https://www.youtube.com/watch?v=cgNvghyR3BA", "rival": "Fire Red"}, {"result": "Victory", "won_rounds": 3, "played_rounds": 4, "raw_points": "804", "beating_factor": "0.75", "won_points": "603", "event": "SSLT 5", "video": "https://www.youtube.com/watch?v=cgNvghyR3BA", "rival": "Fire Red"}], "player": "Marv"}, {"played_battles": 25, "won_battles": 19, "lost_battles": 6, "draw_battles": 0, "win_rate": "76 %", "points_earned": "12585", "wlr": "3.17", "player_level": "39853", "battles_history": [{"result": "Victory", "won_rounds": 3, "played_rounds": 5, "raw_points": "972", "beating_factor": "0.60", "won_points": "583", "event": "SSLT 2", "video": "https://www.youtube.com/watch?v=fAeRytHKAzE", "rival": "Kyorage"}, {"result": "Victory", "won_rounds": 3, "played_rounds": 5, "raw_points": "888", "beating_factor": "0.60", "won_points": "533", "event": "SSLT 2", "video": "https://www.youtube.com/watch?v=fAeRytHKAzE", "rival": "Kyorage"}, {"result": "Victory", "won_rounds": 3, "played_rounds": 5, "raw_points": "1056", "beating_factor": "0.60", "won_points": "634", "event": "SSLT 2", "video": "https://www.youtube.com/watch?v=HRO6tbiXl0s", "rival": "raynarrok"}, {"result": "Victory", "won_rounds": 3, "played_rounds": 3, "raw_points": "720", "beating_factor": "1.00", "won_points": "720", "event": "SSLT 2", "video": "https://www.youtube.com/watch?v=HRO6tbiXl0s", "rival": "raynarrok"}, {"result": "Victory", "won_rounds": 3, "played_rounds": 4, "raw_points": "804", "beating_factor": "0.75", "won_points": "603", "event": "SSLT 2", "video": "https://www.youtube.com/watch?v=Lx9sFTsmNY8", "rival": "Edu Bushi"}, {"result": "Victory", "won_rounds": 3, "played_rounds": 4, "raw_points": "804", "beating_factor": "0.75", "won_points": "603", "event": "SSLT 2", "video": "https://www.youtube.com/watch?v=Lx9sFTsmNY8", "rival": "Edu Bushi"}, {"result": "Victory", "won_rounds": 3, "played_rounds": 5, "raw_points": "972", "beating_factor": "0.60", "won_points": "583", "event": "SSLT 2", "video": "https://www.youtube.com/watch?v=Lx9sFTsmNY8", "rival": "Edu Bushi"}, {"result": "Defeat", "won_rounds": 1, "played_rounds": 4, "raw_points": "660", "beating_factor": "0.25", "won_points": "165", "event": "SSLT 2", "video": "https://www.youtube.com/watch?v=iSKu9AJqFlE", "rival": "raynarrok"}, {"result": "Victory", "won_rounds": 3, "played_rounds": 5, "raw_points": "888", "beating_factor": "0.60", "won_points": "533", "event": "SSLT 2", "video": "https://www.youtube.com/watch?v=iSKu9AJqFlE", "rival": "raynarrok"}, {"result": "Victory", "won_rounds": 3, "played_rounds": 3, "raw_points": "720", "beating_factor": "1.00", "won_points": "720", "event": "SSLT 2", "video": "https://www.youtube.com/watch?v=iSKu9AJqFlE", "rival": "raynarrok"}, {"result": "Victory", "won_rounds": 3, "played_rounds": 5, "raw_points": "972", "beating_factor": "0.60", "won_points": "583", "event": "SSLT 2", "video": "https://www.youtube.com/watch?v=iSKu9AJqFlE", "rival": "raynarrok"}, {"result": "Defeat", "won_rounds": 0, "played_rounds": 3, "raw_points": "420", "beating_factor": "0.10", "won_points": "42", "event": "SSLT 6", "video": "https://youtu.be/aYMnPaA4Ydk", "rival": "Lang"}, {"result": "Defeat", "won_rounds": 0, "played_rounds": 3, "raw_points": "336", "beating_factor": "0.10", "won_points": "34", "event": "SSLT 6", "video": "https://youtu.be/aYMnPaA4Ydk", "rival": "Lang"}, {"result": "Victory", "won_rounds": 3, "played_rounds": 3, "raw_points": "720", "beating_factor": "1.00", "won_points": "720", "event": "SSLT 6", "video": "https://youtu.be/U8u7Qg2jwlU", "rival": "LN Mastodon"}, {"result": "Victory", "won_rounds": 3, "played_rounds": 4, "raw_points": "888", "beating_factor": "0.75", "won_points": "666", "event": "SSLT 6", "video": "https://youtu.be/U8u7Qg2jwlU", "rival": "LN Mastodon"}, {"result": "Victory", "won_rounds": 3, "played_rounds": 3, "raw_points": "720", "beating_factor": "1.00", "won_points": "720", "event": "SSLT 6", "video": "https://youtu.be/nqXqo3_QSBU", "rival": "Ozkuervo"}, {"result": "Victory", "won_rounds": 3, "played_rounds": 3, "raw_points": "720", "beating_factor": "1.00", "won_points": "720", "event": "SSLT 6", "video": "https://youtu.be/nqXqo3_QSBU", "rival": "Ozkuervo"}, {"result": "Victory", "won_rounds": 3, "played_rounds": 3, "raw_points": "720", "beating_factor": "1.00", "won_points": "720", "event": "SSLT 6", "video": "https://youtu.be/mU1N6iViCCM", "rival": "Sebas"}, {"result": "Victory", "won_rounds": 3, "played_rounds": 5, "raw_points": "1056", "beating_factor": "0.60", "won_points": "634", "event": "SSLT 6", "video": "https://youtu.be/mU1N6iViCCM", "rival": "Sebas"}, {"result": "Victory", "won_rounds": 3, "played_rounds": 5, "raw_points": "972", "beating_factor": "0.60", "won_points": "583", "event": "SSLT 6", "video": "https://youtu.be/w2e0I8zFPiU", "rival": "Karol"}, {"result": "Victory", "won_rounds": 3, "played_rounds": 4, "raw_points": "804", "beating_factor": "0.75", "won_points": "603", "event": "SSLT 6", "video": "https://youtu.be/w2e0I8zFPiU", "rival": "Karol"}, {"result": "Victory", "won_rounds": 3, "played_rounds": 5, "raw_points": "888", "beating_factor": "0.60", "won_points": "533", "event": "SSLT 6", "video": "https://youtu.be/w2e0I8zFPiU", "rival": "Karol"}, {"result": "Defeat", "won_rounds": 1, "played_rounds": 4, "raw_points": "660", "beating_factor": "0.25", "won_points": "165", "event": "SSLT 6", "video": "https://youtu.be/fi6gL2gjBFI", "rival": "Lang"}, {"result": "Defeat", "won_rounds": 1, "played_rounds": 4, "raw_points": "576", "beating_factor": "0.25", "won_points": "144", "event": "SSLT 6", "video": "https://youtu.be/fi6gL2gjBFI", "rival": "Lang"}, {"result": "Defeat", "won_rounds": 0, "played_rounds": 3, "raw_points": "420", "beating_factor": "0.10", "won_points": "42", "event": "SSLT 6", "video": "https://youtu.be/fi6gL2gjBFI", "rival": "Lang"}], "player": "Junixart"}, {"played_battles": 42, "won_battles": 22, "lost_battles": 20, "draw_battles": 0, "win_rate": "52 %", "points_earned": "16163", "wlr": "1.10", "player_level": "17779", "battles_history": [{"result": "Victory", "won_rounds": 3, "played_rounds": 5, "raw_points": "972", "beating_factor": "0.60", "won_points": "583", "event": "SSLT 1", "video": "https://www.youtube.com/watch?v=Rm77d1E42fQ", "rival": "wylde"}, {"result": "Defeat", "won_rounds": 0, "played_rounds": 3, "raw_points": "420", "beating_factor": "0.10", "won_points": "42", "event": "SSLT 1", "video": "https://www.youtube.com/watch?v=Rm77d1E42fQ", "rival": "wylde"}, {"result": "Defeat", "won_rounds": 1, "played_rounds": 4, "raw_points": "576", "beating_factor": "0.25", "won_points": "144", "event": "SSLT 1", "video": "https://www.youtube.com/watch?v=Rm77d1E42fQ", "rival": "wylde"}, {"result": "Victory", "won_rounds": 3, "played_rounds": 5, "raw_points": "888", "beating_factor": "0.60", "won_points": "533", "event": "SSLT 1", "video": "https://www.youtube.com/watch?v=o4nlARFmXcA", "rival": "Kovas"}, {"result": "Victory", "won_rounds": 3, "played_rounds": 5, "raw_points": "888", "beating_factor": "0.60", "won_points": "533", "event": "SSLT 1", "video": "https://www.youtube.com/watch?v=o4nlARFmXcA", "rival": "Kovas"}, {"result": "Victory", "won_rounds": 3, "played_rounds": 3, "raw_points": "720", "beating_factor": "1.00", "won_points": "720", "event": "SSLT 1", "video": "https://www.youtube.com/watch?v=o4nlARFmXcA", "rival": "Kovas"}, {"result": "Victory", "won_rounds": 3, "played_rounds": 4, "raw_points": "804", "beating_factor": "0.75", "won_points": "603", "event": "SSLT 1", "video": "https://www.youtube.com/watch?v=QrzOcS2Fseg", "rival": "wylde"}, {"result": "Defeat", "won_rounds": 0, "played_rounds": 3, "raw_points": "336", "beating_factor": "0.10", "won_points": "34", "event": "SSLT 1", "video": "https://www.youtube.com/watch?v=QrzOcS2Fseg", "rival": "wylde"}, {"result": "Defeat", "won_rounds": 0, "played_rounds": 3, "raw_points": "420", "beating_factor": "0.10", "won_points": "42", "event": "SSLT 1", "video": "https://www.youtube.com/watch?v=QrzOcS2Fseg", "rival": "wylde"}, {"result": "Defeat", "won_rounds": 0, "played_rounds": 3, "raw_points": "420", "beating_factor": "0.10", "won_points": "42", "event": "SSLT 1", "video": "https://www.youtube.com/watch?v=QrzOcS2Fseg", "rival": "wylde"}, {"result": "Defeat", "won_rounds": 2, "played_rounds": 5, "raw_points": "732", "beating_factor": "0.40", "won_points": "293", "event": "SSLT 2", "video": "https://www.youtube.com/watch?v=HRO6tbiXl0s", "rival": "Junixart"}, {"result": "Defeat", "won_rounds": 0, "played_rounds": 3, "raw_points": "84", "beating_factor": "0.10", "won_points": "8", "event": "SSLT 2", "video": "https://www.youtube.com/watch?v=HRO6tbiXl0s", "rival": "Junixart"}, {"result": "Victory", "won_rounds": 3, "played_rounds": 4, "raw_points": "804", "beating_factor": "0.75", "won_points": "603", "event": "SSLT 2", "video": "https://www.youtube.com/watch?v=sfar4wH94h8", "rival": "LN Mastodon"}, {"result": "Defeat", "won_rounds": 0, "played_rounds": 3, "raw_points": "252", "beating_factor": "0.10", "won_points": "25", "event": "SSLT 2", "video": "https://www.youtube.com/watch?v=sfar4wH94h8", "rival": "LN Mastodon"}, {"result": "Victory", "won_rounds": 3, "played_rounds": 4, "raw_points": "888", "beating_factor": "0.75", "won_points": "666", "event": "SSLT 2", "video": "https://www.youtube.com/watch?v=sfar4wH94h8", "rival": "LN Mastodon"}, {"result": "Victory", "won_rounds": 3, "played_rounds": 5, "raw_points": "804", "beating_factor": "0.60", "won_points": "482", "event": "SSLT 2", "video": "https://www.youtube.com/watch?v=5U1WvWgWgcw", "rival": "Kyorage"}, {"result": "Defeat", "won_rounds": 2, "played_rounds": 5, "raw_points": "816", "beating_factor": "0.40", "won_points": "326", "event": "SSLT 2", "video": "https://www.youtube.com/watch?v=5U1WvWgWgcw", "rival": "Kyorage"}, {"result": "Victory", "won_rounds": 3, "played_rounds": 5, "raw_points": "972", "beating_factor": "0.60", "won_points": "583", "event": "SSLT 2", "video": "https://www.youtube.com/watch?v=5U1WvWgWgcw", "rival": "Kyorage"}, {"result": "Victory", "won_rounds": 3, "played_rounds": 5, "raw_points": "804", "beating_factor": "0.60", "won_points": "482", "event": "SSLT 2", "video": "https://www.youtube.com/watch?v=gIRTY5-D_mc", "rival": "Edu Bushi"}, {"result": "Defeat", "won_rounds": 1, "played_rounds": 4, "raw_points": "408", "beating_factor": "0.25", "won_points": "102", "event": "SSLT 2", "video": "https://www.youtube.com/watch?v=gIRTY5-D_mc", "rival": "Edu Bushi"}, {"result": "Victory", "won_rounds": 3, "played_rounds": 5, "raw_points": "1056", "beating_factor": "0.60", "won_points": "634", "event": "SSLT 2", "video": "https://www.youtube.com/watch?v=gIRTY5-D_mc", "rival": "Edu Bushi"}, {"result": "Victory", "won_rounds": 3, "played_rounds": 4, "raw_points": "888", "beating_factor": "0.75", "won_points": "666", "event": "SSLT 2", "video": "https://www.youtube.com/watch?v=gIRTY5-D_mc", "rival": "Edu Bushi"}, {"result": "Victory", "won_rounds": 3, "played_rounds": 4, "raw_points": "888", "beating_factor": "0.75", "won_points": "666", "event": "SSLT 2", "video": "https://www.youtube.com/watch?v=iSKu9AJqFlE", "rival": "Junixart"}, {"result": "Defeat", "won_rounds": 2, "played_rounds": 5, "raw_points": "984", "beating_factor": "0.40", "won_points": "394", "event": "SSLT 2", "video": "https://www.youtube.com/watch?v=iSKu9AJqFlE", "rival": "Junixart"}, {"result": "Defeat", "won_rounds": 0, "played_rounds": 3, "raw_points": "336", "beating_factor": "0.10", "won_points": "34", "event": "SSLT 2", "video": "https://www.youtube.com/watch?v=iSKu9AJqFlE", "rival": "Junixart"}, {"result": "Defeat", "won_rounds": 2, "played_rounds": 5, "raw_points": "816", "beating_factor": "0.40", "won_points": "326", "event": "SSLT 2", "video": "https://www.youtube.com/watch?v=iSKu9AJqFlE", "rival": "Junixart"}, {"result": "Victory", "won_rounds": 3, "played_rounds": 4, "raw_points": "888", "beating_factor": "0.75", "won_points": "666", "event": "SSLT 3", "video": "https://www.youtube.com/watch?v=WFUpTT9-F2g", "rival": "Ubitreides"}, {"result": "Defeat", "won_rounds": 0, "played_rounds": 3, "raw_points": "252", "beating_factor": "0.10", "won_points": "25", "event": "SSLT 3", "video": "https://www.youtube.com/watch?v=WFUpTT9-F2g", "rival": "Ubitreides"}, {"result": "Victory", "won_rounds": 3, "played_rounds": 4, "raw_points": "804", "beating_factor": "0.75", "won_points": "603", "event": "SSLT 3", "video": "https://www.youtube.com/watch?v=WFUpTT9-F2g", "rival": "Ubitreides"}, {"result": "Defeat", "won_rounds": 2, "played_rounds": 5, "raw_points": "816", "beating_factor": "0.40", "won_points": "326", "event": "SSLT 3", "video": "https://www.youtube.com/watch?v=EPNpYq3_w74", "rival": "zen-x"}, {"result": "Defeat", "won_rounds": 0, "played_rounds": 3, "raw_points": "252", "beating_factor": "0.10", "won_points": "25", "event": "SSLT 3", "video": "https://www.youtube.com/watch?v=EPNpYq3_w74", "rival": "zen-x"}, {"result": "Victory", "won_rounds": 3, "played_rounds": 3, "raw_points": "720", "beating_factor": "1.00", "won_points": "720", "event": "SSLT 3", "video": "https://www.youtube.com/watch?v=Z7uSsr1SLzs", "rival": "Eche"}, {"result": "Victory", "won_rounds": 3, "played_rounds": 4, "raw_points": "804", "beating_factor": "0.75", "won_points": "603", "event": "SSLT 3", "video": "https://www.youtube.com/watch?v=Z7uSsr1SLzs", "rival": "Eche"}, {"result": "Victory", "won_rounds": 3, "played_rounds": 3, "raw_points": "720", "beating_factor": "1.00", "won_points": "720", "event": "SSLT 3", "video": "https://www.youtube.com/watch?v=nXuZKng3cIU", "rival": "JaffarWolf"}, {"result": "Victory", "won_rounds": 3, "played_rounds": 4, "raw_points": "720", "beating_factor": "0.75", "won_points": "540", "event": "SSLT 3", "video": "https://www.youtube.com/watch?v=nXuZKng3cIU", "rival": "JaffarWolf"}, {"result": "Victory", "won_rounds": 3, "played_rounds": 4, "raw_points": "804", "beating_factor": "0.75", "won_points": "603", "event": "SSLT 3", "video": "https://www.youtube.com/watch?v=jx20RBfMe9s", "rival": "zen-x"}, {"result": "Victory", "won_rounds": 3, "played_rounds": 4, "raw_points": "804", "beating_factor": "0.75", "won_points": "603", "event": "SSLT 3", "video": "https://www.youtube.com/watch?v=jx20RBfMe9s", "rival": "zen-x"}, {"result": "Defeat", "won_rounds": 0, "played_rounds": 3, "raw_points": "252", "beating_factor": "0.10", "won_points": "25", "event": "SSLT 3", "video": "https://www.youtube.com/watch?v=jx20RBfMe9s", "rival": "zen-x"}, {"result": "Victory", "won_rounds": 3, "played_rounds": 4, "raw_points": "804", "beating_factor": "0.75", "won_points": "603", "event": "SSLT 3", "video": "https://www.youtube.com/watch?v=bFys_Gvfb4U", "rival": "zen-x"}, {"result": "Defeat", "won_rounds": 0, "played_rounds": 3, "raw_points": "420", "beating_factor": "0.10", "won_points": "42", "event": "SSLT 3", "video": "https://www.youtube.com/watch?v=bFys_Gvfb4U", "rival": "wylde"}, {"result": "Defeat", "won_rounds": 2, "played_rounds": 5, "raw_points": "816", "beating_factor": "0.40", "won_points": "326", "event": "SSLT 3", "video": "https://www.youtube.com/watch?v=bFys_Gvfb4U", "rival": "wylde"}, {"result": "Defeat", "won_rounds": 1, "played_rounds": 4, "raw_points": "660", "beating_factor": "0.25", "won_points": "165", "event": "SSLT 3", "video": "https://www.youtube.com/watch?v=bFys_Gvfb4U", "rival": "wylde"}], "player": "raynarrok"}, {"played_battles": 14, "won_battles": 8, "lost_battles": 6, "draw_battles": 0, "win_rate": "57 %", "points_earned": "6174", "wlr": "1.33", "player_level": "8232", "battles_history": [{"result": "Victory", "won_rounds": 3, "played_rounds": 4, "raw_points": "888", "beating_factor": "0.75", "won_points": "666", "event": "SSLT 4", "video": "https://www.youtube.com/watch?v=CHpjx9F7Pdk", "rival": "Estebangris"}, {"result": "Victory", "won_rounds": 3, "played_rounds": 3, "raw_points": "720", "beating_factor": "1.00", "won_points": "720", "event": "SSLT 4", "video": "https://www.youtube.com/watch?v=CHpjx9F7Pdk", "rival": "Estebangris"}, {"result": "Victory", "won_rounds": 3, "played_rounds": 4, "raw_points": "804", "beating_factor": "0.75", "won_points": "603", "event": "SSLT 4", "video": "https://www.youtube.com/watch?v=C4ik-me2Ark", "rival": "Leospirandio"}, {"result": "Victory", "won_rounds": 3, "played_rounds": 4, "raw_points": "804", "beating_factor": "0.75", "won_points": "603", "event": "SSLT 4", "video": "https://www.youtube.com/watch?v=C4ik-me2Ark", "rival": "Leospirandio"}, {"result": "Defeat", "won_rounds": 1, "played_rounds": 4, "raw_points": "576", "beating_factor": "0.25", "won_points": "144", "event": "SSLT 4", "video": "https://www.youtube.com/watch?v=A0EVqbG_56g", "rival": "Lang"}, {"result": "Defeat", "won_rounds": 2, "played_rounds": 5, "raw_points": "648", "beating_factor": "0.40", "won_points": "259", "event": "SSLT 4", "video": "https://www.youtube.com/watch?v=A0EVqbG_56g", "rival": "Lang"}, {"result": "Victory", "won_rounds": 3, "played_rounds": 4, "raw_points": "804", "beating_factor": "0.75", "won_points": "603", "event": "SSLT 4", "video": "https://www.youtube.com/watch?v=A0EVqbG_56g", "rival": "Lang"}, {"result": "Victory", "won_rounds": 3, "played_rounds": 5, "raw_points": "972", "beating_factor": "0.60", "won_points": "583", "event": "SSLT 4", "video": "https://www.youtube.com/watch?v=A0EVqbG_56g", "rival": "Lang"}, {"result": "Defeat", "won_rounds": 0, "played_rounds": 3, "raw_points": "252", "beating_factor": "0.10", "won_points": "25", "event": "SSLT 4", "video": "https://www.youtube.com/watch?v=A0EVqbG_56g", "rival": "Lang"}, {"result": "Defeat", "won_rounds": 2, "played_rounds": 5, "raw_points": "816", "beating_factor": "0.40", "won_points": "326", "event": "SSLT 4", "video": "https://www.youtube.com/watch?v=TvgQ44uHXz8", "rival": "Kyorage"}, {"result": "Victory", "won_rounds": 3, "played_rounds": 4, "raw_points": "804", "beating_factor": "0.75", "won_points": "603", "event": "SSLT 4", "video": "https://www.youtube.com/watch?v=TvgQ44uHXz8", "rival": "Kyorage"}, {"result": "Victory", "won_rounds": 3, "played_rounds": 3, "raw_points": "720", "beating_factor": "1.00", "won_points": "720", "event": "SSLT 4", "video": "https://www.youtube.com/watch?v=TvgQ44uHXz8", "rival": "Kyorage"}, {"result": "Defeat", "won_rounds": 2, "played_rounds": 5, "raw_points": "732", "beating_factor": "0.40", "won_points": "293", "event": "SSLT 4", "video": "https://www.youtube.com/watch?v=TvgQ44uHXz8", "rival": "Kyorage"}, {"result": "Defeat", "won_rounds": 0, "played_rounds": 3, "raw_points": "252", "beating_factor": "0.10", "won_points": "25", "event": "SSLT 4", "video": "https://www.youtube.com/watch?v=TvgQ44uHXz8", "rival": "Kyorage"}], "player": "Gontranno"}, {"played_battles": 24, "won_battles": 11, "lost_battles": 13, "draw_battles": 0, "win_rate": "46 %", "points_earned": "9614", "wlr": "0.85", "player_level": "8135", "battles_history": [{"result": "Victory", "won_rounds": 3, "played_rounds": 5, "raw_points": "972", "beating_factor": "0.60", "won_points": "583", "event": "SSLT 3", "video": "https://www.youtube.com/watch?v=ENMj-g3TQ6g", "rival": "Sigfrancis"}, {"result": "Defeat", "won_rounds": 2, "played_rounds": 5, "raw_points": "816", "beating_factor": "0.40", "won_points": "326", "event": "SSLT 3", "video": "https://www.youtube.com/watch?v=ENMj-g3TQ6g", "rival": "Sigfrancis"}, {"result": "Victory", "won_rounds": 3, "played_rounds": 4, "raw_points": "888", "beating_factor": "0.75", "won_points": "666", "event": "SSLT 3", "video": "https://www.youtube.com/watch?v=ENMj-g3TQ6g", "rival": "Sigfrancis"}, {"result": "Victory", "won_rounds": 3, "played_rounds": 5, "raw_points": "1056", "beating_factor": "0.60", "won_points": "634", "event": "SSLT 3", "video": "https://www.youtube.com/watch?v=EPNpYq3_w74", "rival": "raynarrok"}, {"result": "Victory", "won_rounds": 3, "played_rounds": 3, "raw_points": "720", "beating_factor": "1.00", "won_points": "720", "event": "SSLT 3", "video": "https://www.youtube.com/watch?v=EPNpYq3_w74", "rival": "raynarrok"}, {"result": "Defeat", "won_rounds": 2, "played_rounds": 5, "raw_points": "816", "beating_factor": "0.40", "won_points": "326", "event": "SSLT 3", "video": "https://www.youtube.com/watch?v=vl_mNMwesos", "rival": "wylde"}, {"result": "Defeat", "won_rounds": 2, "played_rounds": 5, "raw_points": "900", "beating_factor": "0.40", "won_points": "360", "event": "SSLT 3", "video": "https://www.youtube.com/watch?v=vl_mNMwesos", "rival": "wylde"}, {"result": "Defeat", "won_rounds": 2, "played_rounds": 5, "raw_points": "732", "beating_factor": "0.40", "won_points": "293", "event": "SSLT 3", "video": "https://www.youtube.com/watch?v=vl_mNMwesos", "rival": "wylde"}, {"result": "Defeat", "won_rounds": 1, "played_rounds": 4, "raw_points": "576", "beating_factor": "0.25", "won_points": "144", "event": "SSLT 3", "video": "https://www.youtube.com/watch?v=jx20RBfMe9s", "rival": "raynarrok"}, {"result": "Defeat", "won_rounds": 1, "played_rounds": 4, "raw_points": "576", "beating_factor": "0.25", "won_points": "144", "event": "SSLT 3", "video": "https://www.youtube.com/watch?v=jx20RBfMe9s", "rival": "raynarrok"}, {"result": "Victory", "won_rounds": 3, "played_rounds": 3, "raw_points": "720", "beating_factor": "1.00", "won_points": "720", "event": "SSLT 3", "video": "https://www.youtube.com/watch?v=jx20RBfMe9s", "rival": "raynarrok"}, {"result": "Defeat", "won_rounds": 1, "played_rounds": 4, "raw_points": "576", "beating_factor": "0.25", "won_points": "144", "event": "SSLT 3", "video": "https://www.youtube.com/watch?v=bFys_Gvfb4U", "rival": "raynarrok"}, {"result": "Victory", "won_rounds": 3, "played_rounds": 5, "raw_points": "888", "beating_factor": "0.60", "won_points": "533", "event": "SSLT 5", "video": "https://www.youtube.com/watch?v=Ouqcx_X5tGM", "rival": "Fire Red"}, {"result": "Victory", "won_rounds": 3, "played_rounds": 3, "raw_points": "720", "beating_factor": "1.00", "won_points": "720", "event": "SSLT 5", "video": "https://www.youtube.com/watch?v=Ouqcx_X5tGM", "rival": "Fire Red"}, {"result": "Victory", "won_rounds": 3, "played_rounds": 5, "raw_points": "972", "beating_factor": "0.60", "won_points": "583", "event": "SSLT 5", "video": "https://www.youtube.com/watch?v=omS2WKWXVAw", "rival": "Maxxus"}, {"result": "Victory", "won_rounds": 3, "played_rounds": 5, "raw_points": "972", "beating_factor": "0.60", "won_points": "583", "event": "SSLT 5", "video": "https://www.youtube.com/watch?v=omS2WKWXVAw", "rival": "Maxxus"}, {"result": "Defeat", "won_rounds": 1, "played_rounds": 4, "raw_points": "576", "beating_factor": "0.25", "won_points": "144", "event": "SSLT 5", "video": "https://www.youtube.com/watch?v=2K5L_cYr39M", "rival": "Marv"}, {"result": "Defeat", "won_rounds": 0, "played_rounds": 3, "raw_points": "252", "beating_factor": "0.10", "won_points": "25", "event": "SSLT 5", "video": "https://www.youtube.com/watch?v=2K5L_cYr39M", "rival": "Marv"}, {"result": "Defeat", "won_rounds": 0, "played_rounds": 3, "raw_points": "420", "beating_factor": "0.10", "won_points": "42", "event": "SSLT 5", "video": "https://www.youtube.com/watch?v=2K5L_cYr39M", "rival": "Marv"}, {"result": "Victory", "won_rounds": 3, "played_rounds": 5, "raw_points": "972", "beating_factor": "0.60", "won_points": "583", "event": "SSLT 5", "video": "https://www.youtube.com/watch?v=W_5qMab5ETs", "rival": "Fire Red"}, {"result": "Defeat", "won_rounds": 0, "played_rounds": 3, "raw_points": "168", "beating_factor": "0.10", "won_points": "17", "event": "SSLT 5", "video": "https://www.youtube.com/watch?v=W_5qMab5ETs", "rival": "Fire Red"}, {"result": "Defeat", "won_rounds": 2, "played_rounds": 5, "raw_points": "816", "beating_factor": "0.40", "won_points": "326", "event": "SSLT 5", "video": "https://www.youtube.com/watch?v=W_5qMab5ETs", "rival": "Fire Red"}, {"result": "Victory", "won_rounds": 3, "played_rounds": 4, "raw_points": "804", "beating_factor": "0.75", "won_points": "603", "event": "SSLT 5", "video": "https://www.youtube.com/watch?v=W_5qMab5ETs", "rival": "Fire Red"}, {"result": "Defeat", "won_rounds": 2, "played_rounds": 5, "raw_points": "984", "beating_factor": "0.40", "won_points": "394", "event": "SSLT 5", "video": "https://www.youtube.com/watch?v=W_5qMab5ETs", "rival": "Fire Red"}], "player": "zen-x"}, {"played_battles": 22, "won_battles": 10, "lost_battles": 12, "draw_battles": 0, "win_rate": "45 %", "points_earned": "8975", "wlr": "0.83", "player_level": "7480", "battles_history": [{"result": "Defeat", "won_rounds": 2, "played_rounds": 5, "raw_points": "648", "beating_factor": "0.40", "won_points": "259", "event": "SSLT 2", "video": "https://www.youtube.com/watch?v=fAeRytHKAzE", "rival": "Junixart"}, {"result": "Defeat", "won_rounds": 2, "played_rounds": 5, "raw_points": "816", "beating_factor": "0.40", "won_points": "326", "event": "SSLT 2", "video": "https://www.youtube.com/watch?v=fAeRytHKAzE", "rival": "Junixart"}, {"result": "Defeat", "won_rounds": 2, "played_rounds": 5, "raw_points": "816", "beating_factor": "0.40", "won_points": "326", "event": "SSLT 2", "video": "https://www.youtube.com/watch?v=5U1WvWgWgcw", "rival": "raynarrok"}, {"result": "Victory", "won_rounds": 3, "played_rounds": 5, "raw_points": "888", "beating_factor": "0.60", "won_points": "533", "event": "SSLT 2", "video": "https://www.youtube.com/watch?v=5U1WvWgWgcw", "rival": "raynarrok"}, {"result": "Defeat", "won_rounds": 2, "played_rounds": 5, "raw_points": "648", "beating_factor": "0.40", "won_points": "259", "event": "SSLT 2", "video": "https://www.youtube.com/watch?v=5U1WvWgWgcw", "rival": "raynarrok"}, {"result": "Victory", "won_rounds": 3, "played_rounds": 3, "raw_points": "720", "beating_factor": "1.00", "won_points": "720", "event": "SSLT 4", "video": "https://www.youtube.com/watch?v=6WPUBc5zoZ8", "rival": "Ozkuervo"}, {"result": "Victory", "won_rounds": 3, "played_rounds": 3, "raw_points": "720", "beating_factor": "1.00", "won_points": "720", "event": "SSLT 4", "video": "https://www.youtube.com/watch?v=6WPUBc5zoZ8", "rival": "Ozkuervo"}, {"result": "Defeat", "won_rounds": 2, "played_rounds": 5, "raw_points": "732", "beating_factor": "0.40", "won_points": "293", "event": "SSLT 4", "video": "https://www.youtube.com/watch?v=qqKkNZU-R7Q", "rival": "Lang"}, {"result": "Defeat", "won_rounds": 2, "played_rounds": 5, "raw_points": "984", "beating_factor": "0.40", "won_points": "394", "event": "SSLT 4", "video": "https://www.youtube.com/watch?v=qqKkNZU-R7Q", "rival": "Lang"}, {"result": "Victory", "won_rounds": 3, "played_rounds": 3, "raw_points": "720", "beating_factor": "1.00", "won_points": "720", "event": "SSLT 4", "video": "https://www.youtube.com/watch?v=r86L5se_fNk", "rival": "Estebangris"}, {"result": "Defeat", "won_rounds": 2, "played_rounds": 5, "raw_points": "732", "beating_factor": "0.40", "won_points": "293", "event": "SSLT 4", "video": "https://www.youtube.com/watch?v=r86L5se_fNk", "rival": "Estebangris"}, {"result": "Victory", "won_rounds": 3, "played_rounds": 3, "raw_points": "720", "beating_factor": "1.00", "won_points": "720", "event": "SSLT 4", "video": "https://www.youtube.com/watch?v=r86L5se_fNk", "rival": "Estebangris"}, {"result": "Victory", "won_rounds": 3, "played_rounds": 5, "raw_points": "888", "beating_factor": "0.60", "won_points": "533", "event": "SSLT 4", "video": "https://www.youtube.com/watch?v=qFTVteFzKG0", "rival": "Leospirandio"}, {"result": "Victory", "won_rounds": 3, "played_rounds": 5, "raw_points": "972", "beating_factor": "0.60", "won_points": "583", "event": "SSLT 4", "video": "https://www.youtube.com/watch?v=qFTVteFzKG0", "rival": "Leospirandio"}, {"result": "Victory", "won_rounds": 3, "played_rounds": 5, "raw_points": "972", "beating_factor": "0.60", "won_points": "583", "event": "SSLT 4", "video": "https://www.youtube.com/watch?v=TvgQ44uHXz8", "rival": "Gontranno"}, {"result": "Defeat", "won_rounds": 1, "played_rounds": 4, "raw_points": "660", "beating_factor": "0.25", "won_points": "165", "event": "SSLT 4", "video": "https://www.youtube.com/watch?v=TvgQ44uHXz8", "rival": "Gontranno"}, {"result": "Defeat", "won_rounds": 0, "played_rounds": 3, "raw_points": "336", "beating_factor": "0.10", "won_points": "34", "event": "SSLT 4", "video": "https://www.youtube.com/watch?v=TvgQ44uHXz8", "rival": "Gontranno"}, {"result": "Victory", "won_rounds": 3, "played_rounds": 5, "raw_points": "972", "beating_factor": "0.60", "won_points": "583", "event": "SSLT 4", "video": "https://www.youtube.com/watch?v=TvgQ44uHXz8", "rival": "Gontranno"}, {"result": "Victory", "won_rounds": 3, "played_rounds": 3, "raw_points": "720", "beating_factor": "1.00", "won_points": "720", "event": "SSLT 4", "video": "https://www.youtube.com/watch?v=TvgQ44uHXz8", "rival": "Gontranno"}, {"result": "Defeat", "won_rounds": 1, "played_rounds": 4, "raw_points": "576", "beating_factor": "0.25", "won_points": "144", "event": "SSLT 4", "video": "https://www.youtube.com/watch?v=a73720BuEY4", "rival": "Lang"}, {"result": "Defeat", "won_rounds": 0, "played_rounds": 3, "raw_points": "336", "beating_factor": "0.10", "won_points": "34", "event": "SSLT 4", "video": "https://www.youtube.com/watch?v=a73720BuEY4", "rival": "Lang"}, {"result": "Defeat", "won_rounds": 0, "played_rounds": 3, "raw_points": "336", "beating_factor": "0.10", "won_points": "34", "event": "SSLT 4", "video": "https://www.youtube.com/watch?v=a73720BuEY4", "rival": "Lang"}], "player": "Kyorage"}, {"played_battles": 15, "won_battles": 8, "lost_battles": 7, "draw_battles": 0, "win_rate": "53 %", "points_earned": "6324", "wlr": "1.14", "player_level": "7227", "battles_history": [{"result": "Defeat", "won_rounds": 2, "played_rounds": 5, "raw_points": "984", "beating_factor": "0.40", "won_points": "394", "event": "SSLT 5", "video": "https://www.youtube.com/watch?v=Ouqcx_X5tGM", "rival": "zen-x"}, {"result": "Defeat", "won_rounds": 0, "played_rounds": 3, "raw_points": "420", "beating_factor": "0.10", "won_points": "42", "event": "SSLT 5", "video": "https://www.youtube.com/watch?v=Ouqcx_X5tGM", "rival": "zen-x"}, {"result": "Victory", "won_rounds": 3, "played_rounds": 3, "raw_points": "720", "beating_factor": "1.00", "won_points": "720", "event": "SSLT 5", "video": "https://www.youtube.com/watch?v=yUdiC-QSDB4", "rival": "JaffarWolf"}, {"result": "Victory", "won_rounds": 3, "played_rounds": 4, "raw_points": "888", "beating_factor": "0.75", "won_points": "666", "event": "SSLT 5", "video": "https://www.youtube.com/watch?v=yUdiC-QSDB4", "rival": "JaffarWolf"}, {"result": "Victory", "won_rounds": 3, "played_rounds": 5, "raw_points": "1056", "beating_factor": "0.60", "won_points": "634", "event": "SSLT 5", "video": "https://www.youtube.com/watch?v=CNAaJMsWuiw", "rival": "Maxxus"}, {"result": "Victory", "won_rounds": 3, "played_rounds": 5, "raw_points": "972", "beating_factor": "0.60", "won_points": "583", "event": "SSLT 5", "video": "https://www.youtube.com/watch?v=CNAaJMsWuiw", "rival": "Maxxus"}, {"result": "Defeat", "won_rounds": 2, "played_rounds": 5, "raw_points": "816", "beating_factor": "0.40", "won_points": "326", "event": "SSLT 5", "video": "https://www.youtube.com/watch?v=W_5qMab5ETs", "rival": "zen-x"}, {"result": "Victory", "won_rounds": 3, "played_rounds": 3, "raw_points": "720", "beating_factor": "1.00", "won_points": "720", "event": "SSLT 5", "video": "https://www.youtube.com/watch?v=W_5qMab5ETs", "rival": "zen-x"}, {"result": "Victory", "won_rounds": 3, "played_rounds": 5, "raw_points": "1056", "beating_factor": "0.60", "won_points": "634", "event": "SSLT 5", "video": "https://www.youtube.com/watch?v=W_5qMab5ETs", "rival": "zen-x"}, {"result": "Defeat", "won_rounds": 1, "played_rounds": 4, "raw_points": "492", "beating_factor": "0.25", "won_points": "123", "event": "SSLT 5", "video": "https://www.youtube.com/watch?v=W_5qMab5ETs", "rival": "zen-x"}, {"result": "Victory", "won_rounds": 3, "played_rounds": 5, "raw_points": "972", "beating_factor": "0.60", "won_points": "583", "event": "SSLT 5", "video": "https://www.youtube.com/watch?v=W_5qMab5ETs", "rival": "zen-x"}, {"result": "Defeat", "won_rounds": 1, "played_rounds": 4, "raw_points": "408", "beating_factor": "0.25", "won_points": "102", "event": "SSLT 5", "video": "https://www.youtube.com/watch?v=cgNvghyR3BA", "rival": "Marv"}, {"result": "Victory", "won_rounds": 3, "played_rounds": 4, "raw_points": "804", "beating_factor": "0.75", "won_points": "603", "event": "SSLT 5", "video": "https://www.youtube.com/watch?v=cgNvghyR3BA", "rival": "Marv"}, {"result": "Defeat", "won_rounds": 0, "played_rounds": 3, "raw_points": "504", "beating_factor": "0.10", "won_points": "50", "event": "SSLT 5", "video": "https://www.youtube.com/watch?v=cgNvghyR3BA", "rival": "Marv"}, {"result": "Defeat", "won_rounds": 1, "played_rounds": 4, "raw_points": "576", "beating_factor": "0.25", "won_points": "144", "event": "SSLT 5", "video": "https://www.youtube.com/watch?v=cgNvghyR3BA", "rival": "Marv"}], "player": "Fire Red"}, {"played_battles": 12, "won_battles": 6, "lost_battles": 6, "draw_battles": 0, "win_rate": "50 %", "points_earned": "5354", "wlr": "1.00", "player_level": "5354", "battles_history": [{"result": "Victory", "won_rounds": 3, "played_rounds": 3, "raw_points": "720", "beating_factor": "1.00", "won_points": "720", "event": "SSLT 6", "video": "https://youtu.be/mk41RIgvXuI", "rival": "Sagadalius"}, {"result": "Victory", "won_rounds": 3, "played_rounds": 4, "raw_points": "888", "beating_factor": "0.75", "won_points": "666", "event": "SSLT 6", "video": "https://youtu.be/mk41RIgvXuI", "rival": "Sagadalius"}, {"result": "Victory", "won_rounds": 3, "played_rounds": 4, "raw_points": "888", "beating_factor": "0.75", "won_points": "666", "event": "SSLT 6", "video": "https://youtu.be/BLSF3ZmS5Hk", "rival": "Ozkuervo"}, {"result": "Victory", "won_rounds": 3, "played_rounds": 5, "raw_points": "972", "beating_factor": "0.60", "won_points": "583", "event": "SSLT 6", "video": "https://youtu.be/BLSF3ZmS5Hk", "rival": "Ozkuervo"}, {"result": "Defeat", "won_rounds": 2, "played_rounds": 5, "raw_points": "732", "beating_factor": "0.40", "won_points": "293", "event": "SSLT 6", "video": "https://youtu.be/P_trs_RNRx8", "rival": "Lang"}, {"result": "Victory", "won_rounds": 3, "played_rounds": 5, "raw_points": "1056", "beating_factor": "0.60", "won_points": "634", "event": "SSLT 6", "video": "https://youtu.be/P_trs_RNRx8", "rival": "Lang"}, {"result": "Defeat", "won_rounds": 1, "played_rounds": 4, "raw_points": "660", "beating_factor": "0.25", "won_points": "165", "event": "SSLT 6", "video": "https://youtu.be/P_trs_RNRx8", "rival": "Lang"}, {"result": "Victory", "won_rounds": 3, "played_rounds": 3, "raw_points": "720", "beating_factor": "1.00", "won_points": "720", "event": "SSLT 6", "video": "https://youtu.be/P_trs_RNRx8", "rival": "Lang"}, {"result": "Defeat", "won_rounds": 1, "played_rounds": 4, "raw_points": "492", "beating_factor": "0.25", "won_points": "123", "event": "SSLT 6", "video": "https://youtu.be/P_trs_RNRx8", "rival": "Lang"}, {"result": "Defeat", "won_rounds": 2, "played_rounds": 5, "raw_points": "732", "beating_factor": "0.40", "won_points": "293", "event": "SSLT 6", "video": "https://youtu.be/w2e0I8zFPiU", "rival": "Junixart"}, {"result": "Defeat", "won_rounds": 1, "played_rounds": 4, "raw_points": "660", "beating_factor": "0.25", "won_points": "165", "event": "SSLT 6", "video": "https://youtu.be/w2e0I8zFPiU", "rival": "Junixart"}, {"result": "Defeat", "won_rounds": 2, "played_rounds": 5, "raw_points": "816", "beating_factor": "0.40", "won_points": "326", "event": "SSLT 6", "video": "https://youtu.be/w2e0I8zFPiU", "rival": "Junixart"}], "player": "Karol"}, {"played_battles": 8, "won_battles": 4, "lost_battles": 4, "draw_battles": 0, "win_rate": "50 %", "points_earned": "3691", "wlr": "1.00", "player_level": "3691", "battles_history": [{"result": "Victory", "won_rounds": 3, "played_rounds": 3, "raw_points": "720", "beating_factor": "1.00", "won_points": "720", "event": "SSLT 4", "video": "https://www.youtube.com/watch?v=2Ma4bGcvFzo", "rival": "Sagadalius"}, {"result": "Victory", "won_rounds": 3, "played_rounds": 4, "raw_points": "888", "beating_factor": "0.75", "won_points": "666", "event": "SSLT 4", "video": "https://www.youtube.com/watch?v=2Ma4bGcvFzo", "rival": "Sagadalius"}, {"result": "Defeat", "won_rounds": 1, "played_rounds": 4, "raw_points": "408", "beating_factor": "0.25", "won_points": "102", "event": "SSLT 4", "video": "https://www.youtube.com/watch?v=C4ik-me2Ark", "rival": "Gontranno"}, {"result": "Defeat", "won_rounds": 1, "played_rounds": 4, "raw_points": "576", "beating_factor": "0.25", "won_points": "144", "event": "SSLT 4", "video": "https://www.youtube.com/watch?v=C4ik-me2Ark", "rival": "Gontranno"}, {"result": "Victory", "won_rounds": 3, "played_rounds": 3, "raw_points": "720", "beating_factor": "1.00", "won_points": "720", "event": "SSLT 4", "video": "https://www.youtube.com/watch?v=3czaorzbyIc", "rival": "LN Mastodon"}, {"result": "Victory", "won_rounds": 3, "played_rounds": 3, "raw_points": "720", "beating_factor": "1.00", "won_points": "720", "event": "SSLT 4", "video": "https://www.youtube.com/watch?v=3czaorzbyIc", "rival": "LN Mastodon"}, {"result": "Defeat", "won_rounds": 2, "played_rounds": 5, "raw_points": "816", "beating_factor": "0.40", "won_points": "326", "event": "SSLT 4", "video": "https://www.youtube.com/watch?v=qFTVteFzKG0", "rival": "Kyorage"}, {"result": "Defeat", "won_rounds": 2, "played_rounds": 5, "raw_points": "732", "beating_factor": "0.40", "won_points": "293", "event": "SSLT 4", "video": "https://www.youtube.com/watch?v=qFTVteFzKG0", "rival": "Kyorage"}], "player": "Leospirandio"}, {"played_battles": 9, "won_battles": 4, "lost_battles": 5, "draw_battles": 0, "win_rate": "44 %", "points_earned": "3772", "wlr": "0.80", "player_level": "3018", "battles_history": [{"result": "Victory", "won_rounds": 3, "played_rounds": 3, "raw_points": "720", "beating_factor": "1.00", "won_points": "720", "event": "SSLT 5", "video": "https://www.youtube.com/watch?v=YHgDSz-YR-A", "rival": "Never"}, {"result": "Victory", "won_rounds": 3, "played_rounds": 3, "raw_points": "720", "beating_factor": "1.00", "won_points": "720", "event": "SSLT 5", "video": "https://www.youtube.com/watch?v=YHgDSz-YR-A", "rival": "Never"}, {"result": "Defeat", "won_rounds": 2, "played_rounds": 5, "raw_points": "648", "beating_factor": "0.40", "won_points": "259", "event": "SSLT 5", "video": "https://www.youtube.com/watch?v=omS2WKWXVAw", "rival": "zen-x"}, {"result": "Defeat", "won_rounds": 2, "played_rounds": 5, "raw_points": "732", "beating_factor": "0.40", "won_points": "293", "event": "SSLT 5", "video": "https://www.youtube.com/watch?v=omS2WKWXVAw", "rival": "zen-x"}, {"result": "Defeat", "won_rounds": 0, "played_rounds": 3, "raw_points": "420", "beating_factor": "0.10", "won_points": "42", "event": "SSLT 5", "video": "https://www.youtube.com/watch?v=7bD5GaI2VIA", "rival": "Kovas"}, {"result": "Victory", "won_rounds": 3, "played_rounds": 4, "raw_points": "804", "beating_factor": "0.75", "won_points": "603", "event": "SSLT 5", "video": "https://www.youtube.com/watch?v=7bD5GaI2VIA", "rival": "Kovas"}, {"result": "Victory", "won_rounds": 3, "played_rounds": 5, "raw_points": "972", "beating_factor": "0.60", "won_points": "583", "event": "SSLT 5", "video": "https://www.youtube.com/watch?v=7bD5GaI2VIA", "rival": "Kovas"}, {"result": "Defeat", "won_rounds": 2, "played_rounds": 5, "raw_points": "732", "beating_factor": "0.40", "won_points": "293", "event": "SSLT 5", "video": "https://www.youtube.com/watch?v=CNAaJMsWuiw", "rival": "Fire Red"}, {"result": "Defeat", "won_rounds": 2, "played_rounds": 5, "raw_points": "648", "beating_factor": "0.40", "won_points": "259", "event": "SSLT 5", "video": "https://www.youtube.com/watch?v=CNAaJMsWuiw", "rival": "Fire Red"}], "player": "Maxxus"}, {"played_battles": 16, "won_battles": 6, "lost_battles": 10, "draw_battles": 0, "win_rate": "38 %", "points_earned": "4931", "wlr": "0.60", "player_level": "2958", "battles_history": [{"result": "Victory", "won_rounds": 3, "played_rounds": 4, "raw_points": "804", "beating_factor": "0.75", "won_points": "603", "event": "SSLT 3", "video": "https://www.youtube.com/watch?v=rpwNqy03TyU", "rival": "DonMarlboro"}, {"result": "Defeat", "won_rounds": 1, "played_rounds": 4, "raw_points": "492", "beating_factor": "0.25", "won_points": "123", "event": "SSLT 3", "video": "https://www.youtube.com/watch?v=rpwNqy03TyU", "rival": "DonMarlboro"}, {"result": "Victory", "won_rounds": 3, "played_rounds": 4, "raw_points": "720", "beating_factor": "0.75", "won_points": "540", "event": "SSLT 3", "video": "https://www.youtube.com/watch?v=rpwNqy03TyU", "rival": "DonMarlboro"}, {"result": "Defeat", "won_rounds": 1, "played_rounds": 4, "raw_points": "492", "beating_factor": "0.25", "won_points": "123", "event": "SSLT 3", "video": "https://www.youtube.com/watch?v=z1RFr37KAeE", "rival": "wylde"}, {"result": "Defeat", "won_rounds": 1, "played_rounds": 4, "raw_points": "576", "beating_factor": "0.25", "won_points": "144", "event": "SSLT 3", "video": "https://www.youtube.com/watch?v=z1RFr37KAeE", "rival": "wylde"}, {"result": "Victory", "won_rounds": 3, "played_rounds": 4, "raw_points": "804", "beating_factor": "0.75", "won_points": "603", "event": "SSLT 3", "video": "https://www.youtube.com/watch?v=vldEYFdIE6s", "rival": "Ubitreides"}, {"result": "Defeat", "won_rounds": 2, "played_rounds": 5, "raw_points": "900", "beating_factor": "0.40", "won_points": "360", "event": "SSLT 3", "video": "https://www.youtube.com/watch?v=vldEYFdIE6s", "rival": "Ubitreides"}, {"result": "Victory", "won_rounds": 3, "played_rounds": 5, "raw_points": "972", "beating_factor": "0.60", "won_points": "583", "event": "SSLT 3", "video": "https://www.youtube.com/watch?v=vldEYFdIE6s", "rival": "Ubitreides"}, {"result": "Defeat", "won_rounds": 0, "played_rounds": 3, "raw_points": "336", "beating_factor": "0.10", "won_points": "34", "event": "SSLT 3", "video": "https://www.youtube.com/watch?v=nXuZKng3cIU", "rival": "raynarrok"}, {"result": "Defeat", "won_rounds": 1, "played_rounds": 4, "raw_points": "576", "beating_factor": "0.25", "won_points": "144", "event": "SSLT 3", "video": "https://www.youtube.com/watch?v=nXuZKng3cIU", "rival": "raynarrok"}, {"result": "Victory", "won_rounds": 3, "played_rounds": 4, "raw_points": "888", "beating_factor": "0.75", "won_points": "666", "event": "SSLT 5", "video": "https://www.youtube.com/watch?v=5VfJvK_Hq10", "rival": "Kovas"}, {"result": "Victory", "won_rounds": 3, "played_rounds": 3, "raw_points": "720", "beating_factor": "1.00", "won_points": "720", "event": "SSLT 5", "video": "https://www.youtube.com/watch?v=5VfJvK_Hq10", "rival": "Kovas"}, {"result": "Defeat", "won_rounds": 1, "played_rounds": 4, "raw_points": "492", "beating_factor": "0.25", "won_points": "123", "event": "SSLT 5", "video": "https://www.youtube.com/watch?v=XIHIgK0bGVU", "rival": "Marv"}, {"result": "Defeat", "won_rounds": 0, "played_rounds": 3, "raw_points": "84", "beating_factor": "0.10", "won_points": "8", "event": "SSLT 5", "video": "https://www.youtube.com/watch?v=XIHIgK0bGVU", "rival": "Marv"}, {"result": "Defeat", "won_rounds": 0, "played_rounds": 3, "raw_points": "336", "beating_factor": "0.10", "won_points": "34", "event": "SSLT 5", "video": "https://www.youtube.com/watch?v=yUdiC-QSDB4", "rival": "Fire Red"}, {"result": "Defeat", "won_rounds": 1, "played_rounds": 4, "raw_points": "492", "beating_factor": "0.25", "won_points": "123", "event": "SSLT 5", "video": "https://www.youtube.com/watch?v=yUdiC-QSDB4", "rival": "Fire Red"}], "player": "JaffarWolf"}, {"played_battles": 9, "won_battles": 4, "lost_battles": 5, "draw_battles": 0, "win_rate": "44 %", "points_earned": "3211", "wlr": "0.80", "player_level": "2569", "battles_history": [{"result": "Defeat", "won_rounds": 1, "played_rounds": 4, "raw_points": "492", "beating_factor": "0.25", "won_points": "123", "event": "SSLT 3", "video": "https://www.youtube.com/watch?v=WFUpTT9-F2g", "rival": "raynarrok"}, {"result": "Victory", "won_rounds": 3, "played_rounds": 3, "raw_points": "720", "beating_factor": "1.00", "won_points": "720", "event": "SSLT 3", "video": "https://www.youtube.com/watch?v=WFUpTT9-F2g", "rival": "raynarrok"}, {"result": "Defeat", "won_rounds": 1, "played_rounds": 4, "raw_points": "576", "beating_factor": "0.25", "won_points": "144", "event": "SSLT 3", "video": "https://www.youtube.com/watch?v=WFUpTT9-F2g", "rival": "raynarrok"}, {"result": "Defeat", "won_rounds": 0, "played_rounds": 3, "raw_points": "252", "beating_factor": "0.10", "won_points": "25", "event": "SSLT 3", "video": "https://www.youtube.com/watch?v=Vfju7pwMBwI", "rival": "Sigfrancis"}, {"result": "Victory", "won_rounds": 3, "played_rounds": 5, "raw_points": "888", "beating_factor": "0.60", "won_points": "533", "event": "SSLT 3", "video": "https://www.youtube.com/watch?v=Vfju7pwMBwI", "rival": "Sigfrancis"}, {"result": "Victory", "won_rounds": 3, "played_rounds": 5, "raw_points": "972", "beating_factor": "0.60", "won_points": "583", "event": "SSLT 3", "video": "https://www.youtube.com/watch?v=Vfju7pwMBwI", "rival": "Sigfrancis"}, {"result": "Defeat", "won_rounds": 1, "played_rounds": 4, "raw_points": "492", "beating_factor": "0.25", "won_points": "123", "event": "SSLT 3", "video": "https://www.youtube.com/watch?v=vldEYFdIE6s", "rival": "JaffarWolf"}, {"result": "Victory", "won_rounds": 3, "played_rounds": 5, "raw_points": "1056", "beating_factor": "0.60", "won_points": "634", "event": "SSLT 3", "video": "https://www.youtube.com/watch?v=vldEYFdIE6s", "rival": "JaffarWolf"}, {"result": "Defeat", "won_rounds": 2, "played_rounds": 5, "raw_points": "816", "beating_factor": "0.40", "won_points": "326", "event": "SSLT 3", "video": "https://www.youtube.com/watch?v=vldEYFdIE6s", "rival": "JaffarWolf"}], "player": "Ubitreides"}, {"played_battles": 9, "won_battles": 4, "lost_battles": 5, "draw_battles": 0, "win_rate": "44 %", "points_earned": "3206", "wlr": "0.80", "player_level": "2565", "battles_history": [{"result": "Victory", "won_rounds": 3, "played_rounds": 4, "raw_points": "804", "beating_factor": "0.75", "won_points": "603", "event": "SSLT 6", "video": "https://youtu.be/0aHGYNO6rxE", "rival": "LN Mastodon"}, {"result": "Victory", "won_rounds": 3, "played_rounds": 4, "raw_points": "804", "beating_factor": "0.75", "won_points": "603", "event": "SSLT 6", "video": "https://youtu.be/0aHGYNO6rxE", "rival": "LN Mastodon"}, {"result": "Defeat", "won_rounds": 0, "played_rounds": 3, "raw_points": "252", "beating_factor": "0.10", "won_points": "25", "event": "SSLT 6", "video": "https://youtu.be/tISgzPQCl4w", "rival": "Lang"}, {"result": "Defeat", "won_rounds": 1, "played_rounds": 4, "raw_points": "408", "beating_factor": "0.25", "won_points": "102", "event": "SSLT 6", "video": "https://youtu.be/tISgzPQCl4w", "rival": "Lang"}, {"result": "Victory", "won_rounds": 3, "played_rounds": 5, "raw_points": "972", "beating_factor": "0.60", "won_points": "583", "event": "SSLT 6", "video": "https://youtu.be/59yHzEqGVIY", "rival": "Sagadalius"}, {"result": "Defeat", "won_rounds": 2, "played_rounds": 5, "raw_points": "816", "beating_factor": "0.40", "won_points": "326", "event": "SSLT 6", "video": "https://youtu.be/59yHzEqGVIY", "rival": "Sagadalius"}, {"result": "Victory", "won_rounds": 3, "played_rounds": 4, "raw_points": "804", "beating_factor": "0.75", "won_points": "603", "event": "SSLT 6", "video": "https://youtu.be/59yHzEqGVIY", "rival": "Sagadalius"}, {"result": "Defeat", "won_rounds": 0, "played_rounds": 3, "raw_points": "336", "beating_factor": "0.10", "won_points": "34", "event": "SSLT 6", "video": "https://youtu.be/mU1N6iViCCM", "rival": "Junixart"}, {"result": "Defeat", "won_rounds": 2, "played_rounds": 5, "raw_points": "816", "beating_factor": "0.40", "won_points": "326", "event": "SSLT 6", "video": "https://youtu.be/mU1N6iViCCM", "rival": "Junixart"}], "player": "Sebas"}, {"played_battles": 8, "won_battles": 3, "lost_battles": 5, "draw_battles": 0, "win_rate": "38 %", "points_earned": "2615", "wlr": "0.60", "player_level": "1569", "battles_history": [{"result": "Victory", "won_rounds": 3, "played_rounds": 5, "raw_points": "804", "beating_factor": "0.60", "won_points": "482", "event": "SSLT 3", "video": "https://www.youtube.com/watch?v=8y18kruwQV0", "rival": "wylde"}, {"result": "Defeat", "won_rounds": 2, "played_rounds": 5, "raw_points": "900", "beating_factor": "0.40", "won_points": "360", "event": "SSLT 3", "video": "https://www.youtube.com/watch?v=8y18kruwQV0", "rival": "wylde"}, {"result": "Defeat", "won_rounds": 2, "played_rounds": 5, "raw_points": "816", "beating_factor": "0.40", "won_points": "326", "event": "SSLT 3", "video": "https://www.youtube.com/watch?v=8y18kruwQV0", "rival": "wylde"}, {"result": "Victory", "won_rounds": 3, "played_rounds": 5, "raw_points": "972", "beating_factor": "0.60", "won_points": "583", "event": "SSLT 3", "video": "https://www.youtube.com/watch?v=UeFWWJTwiGM", "rival": "DonMarlboro"}, {"result": "Defeat", "won_rounds": 1, "played_rounds": 4, "raw_points": "492", "beating_factor": "0.25", "won_points": "123", "event": "SSLT 3", "video": "https://www.youtube.com/watch?v=UeFWWJTwiGM", "rival": "DonMarlboro"}, {"result": "Victory", "won_rounds": 3, "played_rounds": 5, "raw_points": "972", "beating_factor": "0.60", "won_points": "583", "event": "SSLT 3", "video": "https://www.youtube.com/watch?v=UeFWWJTwiGM", "rival": "DonMarlboro"}, {"result": "Defeat", "won_rounds": 0, "played_rounds": 3, "raw_points": "336", "beating_factor": "0.10", "won_points": "34", "event": "SSLT 3", "video": "https://www.youtube.com/watch?v=Z7uSsr1SLzs", "rival": "raynarrok"}, {"result": "Defeat", "won_rounds": 1, "played_rounds": 4, "raw_points": "492", "beating_factor": "0.25", "won_points": "123", "event": "SSLT 3", "video": "https://www.youtube.com/watch?v=Z7uSsr1SLzs", "rival": "raynarrok"}], "player": "Eche"}, {"played_battles": 9, "won_battles": 3, "lost_battles": 6, "draw_battles": 0, "win_rate": "33 %", "points_earned": "3070", "wlr": "0.50", "player_level": "1535", "battles_history": [{"result": "Victory", "won_rounds": 3, "played_rounds": 5, "raw_points": "888", "beating_factor": "0.60", "won_points": "533", "event": "SSLT 2", "video": "https://www.youtube.com/watch?v=5X91A4_GiWE", "rival": "LN Mastodon"}, {"result": "Victory", "won_rounds": 3, "played_rounds": 4, "raw_points": "804", "beating_factor": "0.75", "won_points": "603", "event": "SSLT 2", "video": "https://www.youtube.com/watch?v=5X91A4_GiWE", "rival": "LN Mastodon"}, {"result": "Defeat", "won_rounds": 1, "played_rounds": 4, "raw_points": "576", "beating_factor": "0.25", "won_points": "144", "event": "SSLT 2", "video": "https://www.youtube.com/watch?v=Lx9sFTsmNY8", "rival": "Junixart"}, {"result": "Defeat", "won_rounds": 1, "played_rounds": 4, "raw_points": "660", "beating_factor": "0.25", "won_points": "165", "event": "SSLT 2", "video": "https://www.youtube.com/watch?v=Lx9sFTsmNY8", "rival": "Junixart"}, {"result": "Defeat", "won_rounds": 2, "played_rounds": 5, "raw_points": "732", "beating_factor": "0.40", "won_points": "293", "event": "SSLT 2", "video": "https://www.youtube.com/watch?v=Lx9sFTsmNY8", "rival": "Junixart"}, {"result": "Defeat", "won_rounds": 2, "played_rounds": 5, "raw_points": "648", "beating_factor": "0.40", "won_points": "259", "event": "SSLT 2", "video": "https://www.youtube.com/watch?v=gIRTY5-D_mc", "rival": "raynarrok"}, {"result": "Victory", "won_rounds": 3, "played_rounds": 4, "raw_points": "804", "beating_factor": "0.75", "won_points": "603", "event": "SSLT 2", "video": "https://www.youtube.com/watch?v=gIRTY5-D_mc", "rival": "raynarrok"}, {"result": "Defeat", "won_rounds": 2, "played_rounds": 5, "raw_points": "816", "beating_factor": "0.40", "won_points": "326", "event": "SSLT 2", "video": "https://www.youtube.com/watch?v=gIRTY5-D_mc", "rival": "raynarrok"}, {"result": "Defeat", "won_rounds": 1, "played_rounds": 4, "raw_points": "576", "beating_factor": "0.25", "won_points": "144", "event": "SSLT 2", "video": "https://www.youtube.com/watch?v=gIRTY5-D_mc", "rival": "raynarrok"}], "player": "Edu Bushi"}, {"played_battles": 8, "won_battles": 3, "lost_battles": 5, "draw_battles": 0, "win_rate": "38 %", "points_earned": "2546", "wlr": "0.60", "player_level": "1527", "battles_history": [{"result": "Defeat", "won_rounds": 1, "played_rounds": 4, "raw_points": "660", "beating_factor": "0.25", "won_points": "165", "event": "SSLT 4", "video": "https://www.youtube.com/watch?v=CHpjx9F7Pdk", "rival": "Gontranno"}, {"result": "Defeat", "won_rounds": 0, "played_rounds": 3, "raw_points": "420", "beating_factor": "0.10", "won_points": "42", "event": "SSLT 4", "video": "https://www.youtube.com/watch?v=CHpjx9F7Pdk", "rival": "Gontranno"}, {"result": "Victory", "won_rounds": 3, "played_rounds": 5, "raw_points": "1056", "beating_factor": "0.60", "won_points": "634", "event": "SSLT 4", "video": "https://www.youtube.com/watch?v=ZcQJNs-dk-A", "rival": "Sagadalius"}, {"result": "Defeat", "won_rounds": 2, "played_rounds": 5, "raw_points": "984", "beating_factor": "0.40", "won_points": "394", "event": "SSLT 4", "video": "https://www.youtube.com/watch?v=ZcQJNs-dk-A", "rival": "Sagadalius"}, {"result": "Victory", "won_rounds": 3, "played_rounds": 3, "raw_points": "720", "beating_factor": "1.00", "won_points": "720", "event": "SSLT 4", "video": "https://www.youtube.com/watch?v=ZcQJNs-dk-A", "rival": "Sagadalius"}, {"result": "Defeat", "won_rounds": 0, "played_rounds": 3, "raw_points": "252", "beating_factor": "0.10", "won_points": "25", "event": "SSLT 4", "video": "https://www.youtube.com/watch?v=r86L5se_fNk", "rival": "Kyorage"}, {"result": "Victory", "won_rounds": 3, "played_rounds": 5, "raw_points": "888", "beating_factor": "0.60", "won_points": "533", "event": "SSLT 4", "video": "https://www.youtube.com/watch?v=r86L5se_fNk", "rival": "Kyorage"}, {"result": "Defeat", "won_rounds": 0, "played_rounds": 3, "raw_points": "336", "beating_factor": "0.10", "won_points": "34", "event": "SSLT 4", "video": "https://www.youtube.com/watch?v=r86L5se_fNk", "rival": "Kyorage"}], "player": "Estebangris"}, {"played_battles": 6, "won_battles": 2, "lost_battles": 4, "draw_battles": 0, "win_rate": "33 %", "points_earned": "2452", "wlr": "0.50", "player_level": "1226", "battles_history": [{"result": "Defeat", "won_rounds": 2, "played_rounds": 5, "raw_points": "816", "beating_factor": "0.40", "won_points": "326", "event": "SSLT 3", "video": "https://www.youtube.com/watch?v=ENMj-g3TQ6g", "rival": "zen-x"}, {"result": "Victory", "won_rounds": 3, "played_rounds": 5, "raw_points": "972", "beating_factor": "0.60", "won_points": "583", "event": "SSLT 3", "video": "https://www.youtube.com/watch?v=ENMj-g3TQ6g", "rival": "zen-x"}, {"result": "Defeat", "won_rounds": 1, "played_rounds": 4, "raw_points": "408", "beating_factor": "0.25", "won_points": "102", "event": "SSLT 3", "video": "https://www.youtube.com/watch?v=ENMj-g3TQ6g", "rival": "zen-x"}, {"result": "Victory", "won_rounds": 3, "played_rounds": 3, "raw_points": "720", "beating_factor": "1.00", "won_points": "720", "event": "SSLT 3", "video": "https://www.youtube.com/watch?v=Vfju7pwMBwI", "rival": "Ubitreides"}, {"result": "Defeat", "won_rounds": 2, "played_rounds": 5, "raw_points": "900", "beating_factor": "0.40", "won_points": "360", "event": "SSLT 3", "video": "https://www.youtube.com/watch?v=Vfju7pwMBwI", "rival": "Ubitreides"}, {"result": "Defeat", "won_rounds": 2, "played_rounds": 5, "raw_points": "900", "beating_factor": "0.40", "won_points": "360", "event": "SSLT 3", "video": "https://www.youtube.com/watch?v=Vfju7pwMBwI", "rival": "Ubitreides"}], "player": "Sigfrancis"}, {"played_battles": 6, "won_battles": 2, "lost_battles": 4, "draw_battles": 0, "win_rate": "33 %", "points_earned": "2155", "wlr": "0.50", "player_level": "1078", "battles_history": [{"result": "Defeat", "won_rounds": 1, "played_rounds": 4, "raw_points": "492", "beating_factor": "0.25", "won_points": "123", "event": "SSLT 3", "video": "https://www.youtube.com/watch?v=rpwNqy03TyU", "rival": "JaffarWolf"}, {"result": "Victory", "won_rounds": 3, "played_rounds": 4, "raw_points": "888", "beating_factor": "0.75", "won_points": "666", "event": "SSLT 3", "video": "https://www.youtube.com/watch?v=rpwNqy03TyU", "rival": "JaffarWolf"}, {"result": "Defeat", "won_rounds": 1, "played_rounds": 4, "raw_points": "576", "beating_factor": "0.25", "won_points": "144", "event": "SSLT 3", "video": "https://www.youtube.com/watch?v=rpwNqy03TyU", "rival": "JaffarWolf"}, {"result": "Defeat", "won_rounds": 2, "played_rounds": 5, "raw_points": "816", "beating_factor": "0.40", "won_points": "326", "event": "SSLT 3", "video": "https://www.youtube.com/watch?v=UeFWWJTwiGM", "rival": "Eche"}, {"result": "Victory", "won_rounds": 3, "played_rounds": 4, "raw_points": "804", "beating_factor": "0.75", "won_points": "603", "event": "SSLT 3", "video": "https://www.youtube.com/watch?v=UeFWWJTwiGM", "rival": "Eche"}, {"result": "Defeat", "won_rounds": 2, "played_rounds": 5, "raw_points": "732", "beating_factor": "0.40", "won_points": "293", "event": "SSLT 3", "video": "https://www.youtube.com/watch?v=UeFWWJTwiGM", "rival": "Eche"}], "player": "DonMarlboro"}, {"played_battles": 13, "won_battles": 3, "lost_battles": 10, "draw_battles": 0, "win_rate": "23 %", "points_earned": "3559", "wlr": "0.30", "player_level": "1068", "battles_history": [{"result": "Defeat", "won_rounds": 1, "played_rounds": 4, "raw_points": "492", "beating_factor": "0.25", "won_points": "123", "event": "SSLT 1", "video": "https://www.youtube.com/watch?v=C2mgUuDnLaI", "rival": "wylde"}, {"result": "Defeat", "won_rounds": 0, "played_rounds": 3, "raw_points": "252", "beating_factor": "0.10", "won_points": "25", "event": "SSLT 1", "video": "https://www.youtube.com/watch?v=C2mgUuDnLaI", "rival": "wylde"}, {"result": "Defeat", "won_rounds": 0, "played_rounds": 3, "raw_points": "336", "beating_factor": "0.10", "won_points": "34", "event": "SSLT 1", "video": "https://www.youtube.com/watch?v=C2mgUuDnLaI", "rival": "wylde"}, {"result": "Defeat", "won_rounds": 2, "played_rounds": 5, "raw_points": "816", "beating_factor": "0.40", "won_points": "326", "event": "SSLT 1", "video": "https://www.youtube.com/watch?v=o4nlARFmXcA", "rival": "raynarrok"}, {"result": "Defeat", "won_rounds": 2, "played_rounds": 5, "raw_points": "816", "beating_factor": "0.40", "won_points": "326", "event": "SSLT 1", "video": "https://www.youtube.com/watch?v=o4nlARFmXcA", "rival": "raynarrok"}, {"result": "Defeat", "won_rounds": 0, "played_rounds": 3, "raw_points": "504", "beating_factor": "0.10", "won_points": "50", "event": "SSLT 1", "video": "https://www.youtube.com/watch?v=o4nlARFmXcA", "rival": "raynarrok"}, {"result": "Defeat", "won_rounds": 1, "played_rounds": 4, "raw_points": "492", "beating_factor": "0.25", "won_points": "123", "event": "SSLT 5", "video": "https://www.youtube.com/watch?v=5VfJvK_Hq10", "rival": "JaffarWolf"}, {"result": "Defeat", "won_rounds": 0, "played_rounds": 3, "raw_points": "252", "beating_factor": "0.10", "won_points": "25", "event": "SSLT 5", "video": "https://www.youtube.com/watch?v=5VfJvK_Hq10", "rival": "JaffarWolf"}, {"result": "Victory", "won_rounds": 3, "played_rounds": 4, "raw_points": "804", "beating_factor": "0.75", "won_points": "603", "event": "SSLT 5", "video": "https://www.youtube.com/watch?v=B0uq1T7iJf8", "rival": "Megarl"}, {"result": "Victory", "won_rounds": 3, "played_rounds": 3, "raw_points": "720", "beating_factor": "1.00", "won_points": "720", "event": "SSLT 5", "video": "https://www.youtube.com/watch?v=B0uq1T7iJf8", "rival": "Megarl"}, {"result": "Victory", "won_rounds": 3, "played_rounds": 3, "raw_points": "720", "beating_factor": "1.00", "won_points": "720", "event": "SSLT 5", "video": "https://www.youtube.com/watch?v=7bD5GaI2VIA", "rival": "Maxxus"}, {"result": "Defeat", "won_rounds": 1, "played_rounds": 4, "raw_points": "492", "beating_factor": "0.25", "won_points": "123", "event": "SSLT 5", "video": "https://www.youtube.com/watch?v=7bD5GaI2VIA", "rival": "Maxxus"}, {"result": "Defeat", "won_rounds": 2, "played_rounds": 5, "raw_points": "900", "beating_factor": "0.40", "won_points": "360", "event": "SSLT 5", "video": "https://www.youtube.com/watch?v=7bD5GaI2VIA", "rival": "Maxxus"}], "player": "Kovas"}, {"played_battles": 15, "won_battles": 3, "lost_battles": 12, "draw_battles": 0, "win_rate": "20 %", "points_earned": "3245", "wlr": "0.25", "player_level": "811", "battles_history": [{"result": "Defeat", "won_rounds": 2, "played_rounds": 5, "raw_points": "816", "beating_factor": "0.40", "won_points": "326", "event": "SSLT 2", "video": "https://www.youtube.com/watch?v=5X91A4_GiWE", "rival": "Edu Bushi"}, {"result": "Defeat", "won_rounds": 1, "played_rounds": 4, "raw_points": "576", "beating_factor": "0.25", "won_points": "144", "event": "SSLT 2", "video": "https://www.youtube.com/watch?v=5X91A4_GiWE", "rival": "Edu Bushi"}, {"result": "Defeat", "won_rounds": 1, "played_rounds": 4, "raw_points": "576", "beating_factor": "0.25", "won_points": "144", "event": "SSLT 2", "video": "https://www.youtube.com/watch?v=sfar4wH94h8", "rival": "raynarrok"}, {"result": "Victory", "won_rounds": 3, "played_rounds": 3, "raw_points": "720", "beating_factor": "1.00", "won_points": "720", "event": "SSLT 2", "video": "https://www.youtube.com/watch?v=sfar4wH94h8", "rival": "raynarrok"}, {"result": "Defeat", "won_rounds": 1, "played_rounds": 4, "raw_points": "660", "beating_factor": "0.25", "won_points": "165", "event": "SSLT 2", "video": "https://www.youtube.com/watch?v=sfar4wH94h8", "rival": "raynarrok"}, {"result": "Defeat", "won_rounds": 1, "played_rounds": 4, "raw_points": "408", "beating_factor": "0.25", "won_points": "102", "event": "SSLT 4", "video": "https://www.youtube.com/watch?v=K_B5jRkZsAg", "rival": "Lang"}, {"result": "Defeat", "won_rounds": 0, "played_rounds": 3, "raw_points": "252", "beating_factor": "0.10", "won_points": "25", "event": "SSLT 4", "video": "https://www.youtube.com/watch?v=K_B5jRkZsAg", "rival": "Lang"}, {"result": "Victory", "won_rounds": 3, "played_rounds": 5, "raw_points": "888", "beating_factor": "0.60", "won_points": "533", "event": "SSLT 4", "video": "https://www.youtube.com/watch?v=GSDlbOYBEJQ", "rival": "Ozkuervo"}, {"result": "Victory", "won_rounds": 3, "played_rounds": 4, "raw_points": "804", "beating_factor": "0.75", "won_points": "603", "event": "SSLT 4", "video": "https://www.youtube.com/watch?v=GSDlbOYBEJQ", "rival": "Ozkuervo"}, {"result": "Defeat", "won_rounds": 0, "played_rounds": 3, "raw_points": "252", "beating_factor": "0.10", "won_points": "25", "event": "SSLT 4", "video": "https://www.youtube.com/watch?v=3czaorzbyIc", "rival": "Leospirandio"}, {"result": "Defeat", "won_rounds": 0, "played_rounds": 3, "raw_points": "336", "beating_factor": "0.10", "won_points": "34", "event": "SSLT 4", "video": "https://www.youtube.com/watch?v=3czaorzbyIc", "rival": "Leospirandio"}, {"result": "Defeat", "won_rounds": 1, "played_rounds": 4, "raw_points": "576", "beating_factor": "0.25", "won_points": "144", "event": "SSLT 6", "video": "https://youtu.be/0aHGYNO6rxE", "rival": "Sebas"}, {"result": "Defeat", "won_rounds": 1, "played_rounds": 4, "raw_points": "408", "beating_factor": "0.25", "won_points": "102", "event": "SSLT 6", "video": "https://youtu.be/0aHGYNO6rxE", "rival": "Sebas"}, {"result": "Defeat", "won_rounds": 0, "played_rounds": 3, "raw_points": "336", "beating_factor": "0.10", "won_points": "34", "event": "SSLT 6", "video": "https://youtu.be/U8u7Qg2jwlU", "rival": "Junixart"}, {"result": "Defeat", "won_rounds": 1, "played_rounds": 4, "raw_points": "576", "beating_factor": "0.25", "won_points": "144", "event": "SSLT 6", "video": "https://youtu.be/U8u7Qg2jwlU", "rival": "Junixart"}], "player": "LN Mastodon"}, {"played_battles": 10, "won_battles": 2, "lost_battles": 8, "draw_battles": 0, "win_rate": "20 %", "points_earned": "2243", "wlr": "0.25", "player_level": "561", "battles_history": [{"result": "Defeat", "won_rounds": 0, "played_rounds": 3, "raw_points": "336", "beating_factor": "0.10", "won_points": "34", "event": "SSLT 4", "video": "https://www.youtube.com/watch?v=2Ma4bGcvFzo", "rival": "Leospirandio"}, {"result": "Defeat", "won_rounds": 1, "played_rounds": 4, "raw_points": "576", "beating_factor": "0.25", "won_points": "144", "event": "SSLT 4", "video": "https://www.youtube.com/watch?v=2Ma4bGcvFzo", "rival": "Leospirandio"}, {"result": "Defeat", "won_rounds": 2, "played_rounds": 5, "raw_points": "816", "beating_factor": "0.40", "won_points": "326", "event": "SSLT 4", "video": "https://www.youtube.com/watch?v=ZcQJNs-dk-A", "rival": "Estebangris"}, {"result": "Victory", "won_rounds": 3, "played_rounds": 5, "raw_points": "888", "beating_factor": "0.60", "won_points": "533", "event": "SSLT 4", "video": "https://www.youtube.com/watch?v=ZcQJNs-dk-A", "rival": "Estebangris"}, {"result": "Defeat", "won_rounds": 0, "played_rounds": 3, "raw_points": "336", "beating_factor": "0.10", "won_points": "34", "event": "SSLT 4", "video": "https://www.youtube.com/watch?v=ZcQJNs-dk-A", "rival": "Estebangris"}, {"result": "Defeat", "won_rounds": 0, "played_rounds": 3, "raw_points": "252", "beating_factor": "0.10", "won_points": "25", "event": "SSLT 6", "video": "https://youtu.be/mk41RIgvXuI", "rival": "Karol"}, {"result": "Defeat", "won_rounds": 1, "played_rounds": 4, "raw_points": "576", "beating_factor": "0.25", "won_points": "144", "event": "SSLT 6", "video": "https://youtu.be/mk41RIgvXuI", "rival": "Karol"}, {"result": "Defeat", "won_rounds": 2, "played_rounds": 5, "raw_points": "816", "beating_factor": "0.40", "won_points": "326", "event": "SSLT 6", "video": "https://youtu.be/59yHzEqGVIY", "rival": "Sebas"}, {"result": "Victory", "won_rounds": 3, "played_rounds": 5, "raw_points": "888", "beating_factor": "0.60", "won_points": "533", "event": "SSLT 6", "video": "https://youtu.be/59yHzEqGVIY", "rival": "Sebas"}, {"result": "Defeat", "won_rounds": 1, "played_rounds": 4, "raw_points": "576", "beating_factor": "0.25", "won_points": "144", "event": "SSLT 6", "video": "https://youtu.be/59yHzEqGVIY", "rival": "Sebas"}], "player": "Sagadalius"}, {"played_battles": 8, "won_battles": 0, "lost_battles": 8, "draw_battles": 0, "win_rate": "0 %", "points_earned": "970", "wlr": "0.12", "player_level": "121", "battles_history": [{"result": "Defeat", "won_rounds": 0, "played_rounds": 3, "raw_points": "252", "beating_factor": "0.10", "won_points": "25", "event": "SSLT 4", "video": "https://www.youtube.com/watch?v=6WPUBc5zoZ8", "rival": "Kyorage"}, {"result": "Defeat", "won_rounds": 0, "played_rounds": 3, "raw_points": "168", "beating_factor": "0.10", "won_points": "17", "event": "SSLT 4", "video": "https://www.youtube.com/watch?v=6WPUBc5zoZ8", "rival": "Kyorage"}, {"result": "Defeat", "won_rounds": 2, "played_rounds": 5, "raw_points": "900", "beating_factor": "0.40", "won_points": "360", "event": "SSLT 4", "video": "https://www.youtube.com/watch?v=GSDlbOYBEJQ", "rival": "LN Mastodon"}, {"result": "Defeat", "won_rounds": 1, "played_rounds": 4, "raw_points": "492", "beating_factor": "0.25", "won_points": "123", "event": "SSLT 4", "video": "https://www.youtube.com/watch?v=GSDlbOYBEJQ", "rival": "LN Mastodon"}, {"result": "Defeat", "won_rounds": 1, "played_rounds": 4, "raw_points": "576", "beating_factor": "0.25", "won_points": "144", "event": "SSLT 6", "video": "https://youtu.be/BLSF3ZmS5Hk", "rival": "Karol"}, {"result": "Defeat", "won_rounds": 2, "played_rounds": 5, "raw_points": "648", "beating_factor": "0.40", "won_points": "259", "event": "SSLT 6", "video": "https://youtu.be/BLSF3ZmS5Hk", "rival": "Karol"}, {"result": "Defeat", "won_rounds": 0, "played_rounds": 3, "raw_points": "252", "beating_factor": "0.10", "won_points": "25", "event": "SSLT 6", "video": "https://youtu.be/nqXqo3_QSBU", "rival": "Junixart"}, {"result": "Defeat", "won_rounds": 0, "played_rounds": 3, "raw_points": "168", "beating_factor": "0.10", "won_points": "17", "event": "SSLT 6", "video": "https://youtu.be/nqXqo3_QSBU", "rival": "Junixart"}], "player": "Ozkuervo"}, {"played_battles": 4, "won_battles": 0, "lost_battles": 4, "draw_battles": 0, "win_rate": "0 %", "points_earned": "280", "wlr": "0.25", "player_level": "70", "battles_history": [{"result": "Defeat", "won_rounds": 1, "played_rounds": 4, "raw_points": "324", "beating_factor": "0.25", "won_points": "81", "event": "SSLT 5", "video": "https://www.youtube.com/watch?v=eIoutvA67tM", "rival": "Marv"}, {"result": "Defeat", "won_rounds": 0, "played_rounds": 3, "raw_points": "336", "beating_factor": "0.10", "won_points": "34", "event": "SSLT 5", "video": "https://www.youtube.com/watch?v=eIoutvA67tM", "rival": "Marv"}, {"result": "Defeat", "won_rounds": 1, "played_rounds": 4, "raw_points": "492", "beating_factor": "0.25", "won_points": "123", "event": "SSLT 5", "video": "https://www.youtube.com/watch?v=B0uq1T7iJf8", "rival": "Kovas"}, {"result": "Defeat", "won_rounds": 0, "played_rounds": 3, "raw_points": "420", "beating_factor": "0.10", "won_points": "42", "event": "SSLT 5", "video": "https://www.youtube.com/watch?v=B0uq1T7iJf8", "rival": "Kovas"}], "player": "Megarl"}, {"played_battles": 2, "won_battles": 0, "lost_battles": 2, "draw_battles": 0, "win_rate": "0 %", "points_earned": "34", "wlr": "0.50", "player_level": "17", "battles_history": [{"result": "Defeat", "won_rounds": 0, "played_rounds": 3, "raw_points": "252", "beating_factor": "0.10", "won_points": "25", "event": "SSLT 5", "video": "https://www.youtube.com/watch?v=YHgDSz-YR-A", "rival": "Maxxus"}, {"result": "Defeat", "won_rounds": 0, "played_rounds": 3, "raw_points": "84", "beating_factor": "0.10", "won_points": "8", "event": "SSLT 5", "video": "https://www.youtube.com/watch?v=YHgDSz-YR-A", "rival": "Maxxus"}], "player": "Never"}]