[{"played_battles": 11, "won_battles": 10, "lost_battles": 1, "draw_battles": 0, "win_rate": "90.91 %", "points_earned": "6798", "wlr": "10.00", "player_level": "67982", "battles_history": [{"result": "Defeat", "won_rounds": 2, "played_rounds": 5, "raw_points": "816", "beating_factor": "0.40", "lvl_factor": "1.16", "won_points": "379", "event": "SSLT 7", "video": "PC", "rival": "wylde"}, {"result": "Victory", "won_rounds": 3, "played_rounds": 4, "raw_points": "888", "beating_factor": "0.75", "lvl_factor": "1.16", "won_points": "775", "event": "SSLT 7", "video": "PC", "rival": "wylde"}, {"result": "Victory", "won_rounds": 3, "played_rounds": 5, "raw_points": "972", "beating_factor": "0.60", "lvl_factor": "1.06", "won_points": "619", "event": "SSLT 7", "video": "PC", "rival": "wylde"}, {"result": "Victory", "won_rounds": 3, "played_rounds": 3, "raw_points": "720", "beating_factor": "1.00", "lvl_factor": "0.95", "won_points": "687", "event": "SSLT 7", "video": "PC", "rival": "JaffarWolf"}, {"result": "Victory", "won_rounds": 3, "played_rounds": 3, "raw_points": "720", "beating_factor": "1.00", "lvl_factor": "0.93", "won_points": "672", "event": "SSLT 7", "video": "PC", "rival": "JaffarWolf"}, {"result": "Victory", "won_rounds": 3, "played_rounds": 3, "raw_points": "720", "beating_factor": "1.00", "lvl_factor": "0.95", "won_points": "685", "event": "SSLT 7", "video": "PC", "rival": "Sigfrancis"}, {"result": "Victory", "won_rounds": 3, "played_rounds": 3, "raw_points": "720", "beating_factor": "1.00", "lvl_factor": "0.94", "won_points": "675", "event": "SSLT 7", "video": "PC", "rival": "Sigfrancis"}, {"result": "Victory", "won_rounds": 3, "played_rounds": 4, "raw_points": "888", "beating_factor": "0.75", "lvl_factor": "0.93", "won_points": "616", "event": "SSLT 7", "video": "PC", "rival": "Sigfrancis"}, {"result": "Victory", "won_rounds": 3, "played_rounds": 5, "raw_points": "972", "beating_factor": "0.60", "lvl_factor": "0.93", "won_points": "542", "event": "SSLT 7", "video": "PC", "rival": "DonMarlboro"}, {"result": "Victory", "won_rounds": 3, "played_rounds": 5, "raw_points": "972", "beating_factor": "0.60", "lvl_factor": "0.92", "won_points": "538", "event": "SSLT 7", "video": "PC", "rival": "DonMarlboro"}, {"result": "Victory", "won_rounds": 3, "played_rounds": 4, "raw_points": "888", "beating_factor": "0.75", "lvl_factor": "0.92", "won_points": "610", "event": "SSLT 7", "video": "PC", "rival": "DonMarlboro"}], "player_stats": [{"rival": "wylde", "played_battles": 3, "won_battles": 2, "lost_battles": 1, "draw_battles": 0, "win_rate": "67 %"}, {"rival": "JaffarWolf", "played_battles": 2, "won_battles": 2, "lost_battles": 0, "draw_battles": 0, "win_rate": "100 %"}, {"rival": "Sigfrancis", "played_battles": 3, "won_battles": 3, "lost_battles": 0, "draw_battles": 0, "win_rate": "100 %"}, {"rival": "DonMarlboro", "played_battles": 3, "won_battles": 3, "lost_battles": 0, "draw_battles": 0, "win_rate": "100 %"}], "player": "Camus"}, {"played_battles": 11, "won_battles": 10, "lost_battles": 1, "draw_battles": 0, "win_rate": "90.91 %", "points_earned": "6227", "wlr": "10.00", "player_level": "62274", "battles_history": [{"result": "Victory", "won_rounds": 3, "played_rounds": 4, "raw_points": "888", "beating_factor": "0.75", "lvl_factor": "1.00", "won_points": "666", "event": "SSLT 5", "video": "PC", "rival": "Megarl"}, {"result": "Victory", "won_rounds": 3, "played_rounds": 3, "raw_points": "720", "beating_factor": "1.00", "lvl_factor": "0.81", "won_points": "584", "event": "SSLT 5", "video": "PC", "rival": "Megarl"}, {"result": "Victory", "won_rounds": 3, "played_rounds": 4, "raw_points": "720", "beating_factor": "0.75", "lvl_factor": "0.91", "won_points": "489", "event": "SSLT 5", "video": "PC", "rival": "JaffarWolf"}, {"result": "Victory", "won_rounds": 3, "played_rounds": 3, "raw_points": "720", "beating_factor": "1.00", "lvl_factor": "0.90", "won_points": "647", "event": "SSLT 5", "video": "PC", "rival": "JaffarWolf"}, {"result": "Victory", "won_rounds": 3, "played_rounds": 4, "raw_points": "804", "beating_factor": "0.75", "lvl_factor": "0.92", "won_points": "553", "event": "SSLT 5", "video": "PC", "rival": "zen-x"}, {"result": "Victory", "won_rounds": 3, "played_rounds": 3, "raw_points": "720", "beating_factor": "1.00", "lvl_factor": "0.91", "won_points": "656", "event": "SSLT 5", "video": "PC", "rival": "zen-x"}, {"result": "Victory", "won_rounds": 3, "played_rounds": 3, "raw_points": "720", "beating_factor": "1.00", "lvl_factor": "0.91", "won_points": "652", "event": "SSLT 5", "video": "PC", "rival": "zen-x"}, {"result": "Victory", "won_rounds": 3, "played_rounds": 4, "raw_points": "888", "beating_factor": "0.75", "lvl_factor": "0.93", "won_points": "620", "event": "SSLT 5", "video": "PC", "rival": "Fire Red"}, {"result": "Defeat", "won_rounds": 1, "played_rounds": 4, "raw_points": "492", "beating_factor": "0.25", "lvl_factor": "0.92", "won_points": "113", "event": "SSLT 5", "video": "PC", "rival": "Fire Red"}, {"result": "Victory", "won_rounds": 3, "played_rounds": 3, "raw_points": "720", "beating_factor": "1.00", "lvl_factor": "0.95", "won_points": "683", "event": "SSLT 5", "video": "PC", "rival": "Fire Red"}, {"result": "Victory", "won_rounds": 3, "played_rounds": 4, "raw_points": "804", "beating_factor": "0.75", "lvl_factor": "0.94", "won_points": "565", "event": "SSLT 5", "video": "PC", "rival": "Fire Red"}], "player_stats": [{"rival": "Megarl", "played_battles": 2, "won_battles": 2, "lost_battles": 0, "draw_battles": 0, "win_rate": "100 %"}, {"rival": "JaffarWolf", "played_battles": 2, "won_battles": 2, "lost_battles": 0, "draw_battles": 0, "win_rate": "100 %"}, {"rival": "zen-x", "played_battles": 3, "won_battles": 3, "lost_battles": 0, "draw_battles": 0, "win_rate": "100 %"}, {"rival": "Fire Red", "played_battles": 4, "won_battles": 3, "lost_battles": 1, "draw_battles": 0, "win_rate": "75 %"}], "player": "Marv"}, {"played_battles": 29, "won_battles": 22, "lost_battles": 7, "draw_battles": 0, "win_rate": "75.86 %", "points_earned": "14992", "wlr": "3.14", "player_level": "47116", "battles_history": [{"result": "Defeat", "won_rounds": 2, "played_rounds": 5, "raw_points": "732", "beating_factor": "0.40", "lvl_factor": "1.00", "won_points": "293", "event": "SSLT 1", "video": "PC", "rival": "raynarrok"}, {"result": "Victory", "won_rounds": 3, "played_rounds": 3, "raw_points": "720", "beating_factor": "1.00", "lvl_factor": "1.19", "won_points": "856", "event": "SSLT 1", "video": "PC", "rival": "raynarrok"}, {"result": "Victory", "won_rounds": 3, "played_rounds": 4, "raw_points": "888", "beating_factor": "0.75", "lvl_factor": "1.00", "won_points": "666", "event": "SSLT 1", "video": "PC", "rival": "raynarrok"}, {"result": "Victory", "won_rounds": 3, "played_rounds": 4, "raw_points": "888", "beating_factor": "0.75", "lvl_factor": "0.87", "won_points": "582", "event": "SSLT 1", "video": "PC", "rival": "Kovas"}, {"result": "Victory", "won_rounds": 3, "played_rounds": 3, "raw_points": "720", "beating_factor": "1.00", "lvl_factor": "0.86", "won_points": "618", "event": "SSLT 1", "video": "PC", "rival": "Kovas"}, {"result": "Victory", "won_rounds": 3, "played_rounds": 3, "raw_points": "720", "beating_factor": "1.00", "lvl_factor": "0.85", "won_points": "611", "event": "SSLT 1", "video": "PC", "rival": "Kovas"}, {"result": "Defeat", "won_rounds": 1, "played_rounds": 4, "raw_points": "576", "beating_factor": "0.25", "lvl_factor": "0.97", "won_points": "139", "event": "SSLT 1", "video": "PC", "rival": "raynarrok"}, {"result": "Victory", "won_rounds": 3, "played_rounds": 3, "raw_points": "720", "beating_factor": "1.00", "lvl_factor": "1.00", "won_points": "720", "event": "SSLT 1", "video": "PC", "rival": "raynarrok"}, {"result": "Victory", "won_rounds": 3, "played_rounds": 3, "raw_points": "720", "beating_factor": "1.00", "lvl_factor": "0.98", "won_points": "703", "event": "SSLT 1", "video": "PC", "rival": "raynarrok"}, {"result": "Victory", "won_rounds": 3, "played_rounds": 3, "raw_points": "720", "beating_factor": "1.00", "lvl_factor": "0.96", "won_points": "690", "event": "SSLT 1", "video": "PC", "rival": "raynarrok"}, {"result": "Defeat", "won_rounds": 2, "played_rounds": 5, "raw_points": "816", "beating_factor": "0.40", "lvl_factor": "0.85", "won_points": "277", "event": "SSLT 3", "video": "PC", "rival": "Eche"}, {"result": "Victory", "won_rounds": 3, "played_rounds": 5, "raw_points": "888", "beating_factor": "0.60", "lvl_factor": "1.05", "won_points": "560", "event": "SSLT 3", "video": "PC", "rival": "Eche"}, {"result": "Victory", "won_rounds": 3, "played_rounds": 5, "raw_points": "972", "beating_factor": "0.60", "lvl_factor": "0.95", "won_points": "556", "event": "SSLT 3", "video": "PC", "rival": "Eche"}, {"result": "Victory", "won_rounds": 3, "played_rounds": 4, "raw_points": "804", "beating_factor": "0.75", "lvl_factor": "0.98", "won_points": "591", "event": "SSLT 3", "video": "PC", "rival": "JaffarWolf"}, {"result": "Victory", "won_rounds": 3, "played_rounds": 4, "raw_points": "804", "beating_factor": "0.75", "lvl_factor": "0.95", "won_points": "570", "event": "SSLT 3", "video": "PC", "rival": "JaffarWolf"}, {"result": "Victory", "won_rounds": 3, "played_rounds": 5, "raw_points": "888", "beating_factor": "0.60", "lvl_factor": "1.00", "won_points": "533", "event": "SSLT 3", "video": "PC", "rival": "zen-x"}, {"result": "Victory", "won_rounds": 3, "played_rounds": 5, "raw_points": "888", "beating_factor": "0.60", "lvl_factor": "0.97", "won_points": "518", "event": "SSLT 3", "video": "PC", "rival": "zen-x"}, {"result": "Victory", "won_rounds": 3, "played_rounds": 5, "raw_points": "972", "beating_factor": "0.60", "lvl_factor": "0.95", "won_points": "555", "event": "SSLT 3", "video": "PC", "rival": "zen-x"}, {"result": "Victory", "won_rounds": 3, "played_rounds": 3, "raw_points": "720", "beating_factor": "1.00", "lvl_factor": "0.96", "won_points": "689", "event": "SSLT 3", "video": "PC", "rival": "raynarrok"}, {"result": "Victory", "won_rounds": 3, "played_rounds": 5, "raw_points": "888", "beating_factor": "0.60", "lvl_factor": "0.95", "won_points": "507", "event": "SSLT 3", "video": "PC", "rival": "raynarrok"}, {"result": "Victory", "won_rounds": 3, "played_rounds": 4, "raw_points": "720", "beating_factor": "0.75", "lvl_factor": "0.95", "won_points": "510", "event": "SSLT 3", "video": "PC", "rival": "raynarrok"}, {"result": "Victory", "won_rounds": 3, "played_rounds": 5, "raw_points": "888", "beating_factor": "0.60", "lvl_factor": "0.84", "won_points": "446", "event": "SSLT 7", "video": "PC", "rival": "Camus"}, {"result": "Defeat", "won_rounds": 1, "played_rounds": 4, "raw_points": "492", "beating_factor": "0.25", "lvl_factor": "0.84", "won_points": "103", "event": "SSLT 7", "video": "PC", "rival": "Camus"}, {"result": "Defeat", "won_rounds": 2, "played_rounds": 5, "raw_points": "732", "beating_factor": "0.40", "lvl_factor": "0.94", "won_points": "275", "event": "SSLT 7", "video": "PC", "rival": "Camus"}, {"result": "Victory", "won_rounds": 3, "played_rounds": 3, "raw_points": "720", "beating_factor": "1.00", "lvl_factor": "0.90", "won_points": "646", "event": "SSLT 7", "video": "PC", "rival": "Kovas"}, {"result": "Victory", "won_rounds": 3, "played_rounds": 3, "raw_points": "720", "beating_factor": "1.00", "lvl_factor": "0.89", "won_points": "643", "event": "SSLT 7", "video": "PC", "rival": "Kovas"}, {"result": "Defeat", "won_rounds": 2, "played_rounds": 5, "raw_points": "900", "beating_factor": "0.40", "lvl_factor": "0.92", "won_points": "330", "event": "SSLT 7", "video": "PC", "rival": "DonMarlboro"}, {"result": "Victory", "won_rounds": 3, "played_rounds": 3, "raw_points": "720", "beating_factor": "1.00", "lvl_factor": "0.93", "won_points": "671", "event": "SSLT 7", "video": "PC", "rival": "DonMarlboro"}, {"result": "Defeat", "won_rounds": 1, "played_rounds": 4, "raw_points": "576", "beating_factor": "0.25", "lvl_factor": "0.92", "won_points": "133", "event": "SSLT 7", "video": "PC", "rival": "DonMarlboro"}], "player_stats": [{"rival": "raynarrok", "played_battles": 10, "won_battles": 8, "lost_battles": 2, "draw_battles": 0, "win_rate": "80 %"}, {"rival": "Kovas", "played_battles": 5, "won_battles": 5, "lost_battles": 0, "draw_battles": 0, "win_rate": "100 %"}, {"rival": "Eche", "played_battles": 3, "won_battles": 2, "lost_battles": 1, "draw_battles": 0, "win_rate": "67 %"}, {"rival": "JaffarWolf", "played_battles": 2, "won_battles": 2, "lost_battles": 0, "draw_battles": 0, "win_rate": "100 %"}, {"rival": "zen-x", "played_battles": 3, "won_battles": 3, "lost_battles": 0, "draw_battles": 0, "win_rate": "100 %"}, {"rival": "Camus", "played_battles": 3, "won_battles": 1, "lost_battles": 2, "draw_battles": 0, "win_rate": "33 %"}, {"rival": "DonMarlboro", "played_battles": 3, "won_battles": 1, "lost_battles": 2, "draw_battles": 0, "win_rate": "33 %"}], "player": "wylde"}, {"played_battles": 26, "won_battles": 14, "lost_battles": 12, "draw_battles": 0, "win_rate": "53.85 %", "points_earned": "11233", "wlr": "1.17", "player_level": "13105", "battles_history": [{"result": "Defeat", "won_rounds": 2, "played_rounds": 5, "raw_points": "984", "beating_factor": "0.40", "lvl_factor": "1.08", "won_points": "425", "event": "SSLT 5", "video": "PC", "rival": "zen-x"}, {"result": "Defeat", "won_rounds": 0, "played_rounds": 3, "raw_points": "420", "beating_factor": "0.10", "lvl_factor": "1.09", "won_points": "46", "event": "SSLT 5", "video": "PC", "rival": "zen-x"}, {"result": "Victory", "won_rounds": 3, "played_rounds": 3, "raw_points": "720", "beating_factor": "1.00", "lvl_factor": "1.08", "won_points": "778", "event": "SSLT 5", "video": "PC", "rival": "JaffarWolf"}, {"result": "Victory", "won_rounds": 3, "played_rounds": 4, "raw_points": "888", "beating_factor": "0.75", "lvl_factor": "1.01", "won_points": "674", "event": "SSLT 5", "video": "PC", "rival": "JaffarWolf"}, {"result": "Victory", "won_rounds": 3, "played_rounds": 5, "raw_points": "1056", "beating_factor": "0.60", "lvl_factor": "1.01", "won_points": "642", "event": "SSLT 5", "video": "PC", "rival": "Maxxus"}, {"result": "Victory", "won_rounds": 3, "played_rounds": 5, "raw_points": "972", "beating_factor": "0.60", "lvl_factor": "0.98", "won_points": "572", "event": "SSLT 5", "video": "PC", "rival": "Maxxus"}, {"result": "Defeat", "won_rounds": 2, "played_rounds": 5, "raw_points": "816", "beating_factor": "0.40", "lvl_factor": "0.96", "won_points": "314", "event": "SSLT 5", "video": "PC", "rival": "zen-x"}, {"result": "Victory", "won_rounds": 3, "played_rounds": 3, "raw_points": "720", "beating_factor": "1.00", "lvl_factor": "0.99", "won_points": "710", "event": "SSLT 5", "video": "PC", "rival": "zen-x"}, {"result": "Victory", "won_rounds": 3, "played_rounds": 5, "raw_points": "1056", "beating_factor": "0.60", "lvl_factor": "0.97", "won_points": "616", "event": "SSLT 5", "video": "PC", "rival": "zen-x"}, {"result": "Defeat", "won_rounds": 1, "played_rounds": 4, "raw_points": "492", "beating_factor": "0.25", "lvl_factor": "0.96", "won_points": "118", "event": "SSLT 5", "video": "PC", "rival": "zen-x"}, {"result": "Victory", "won_rounds": 3, "played_rounds": 5, "raw_points": "972", "beating_factor": "0.60", "lvl_factor": "0.98", "won_points": "570", "event": "SSLT 5", "video": "PC", "rival": "zen-x"}, {"result": "Defeat", "won_rounds": 1, "played_rounds": 4, "raw_points": "408", "beating_factor": "0.25", "lvl_factor": "1.07", "won_points": "109", "event": "SSLT 5", "video": "PC", "rival": "Marv"}, {"result": "Victory", "won_rounds": 3, "played_rounds": 4, "raw_points": "804", "beating_factor": "0.75", "lvl_factor": "1.08", "won_points": "651", "event": "SSLT 5", "video": "PC", "rival": "Marv"}, {"result": "Defeat", "won_rounds": 0, "played_rounds": 3, "raw_points": "504", "beating_factor": "0.10", "lvl_factor": "1.05", "won_points": "53", "event": "SSLT 5", "video": "PC", "rival": "Marv"}, {"result": "Defeat", "won_rounds": 1, "played_rounds": 4, "raw_points": "576", "beating_factor": "0.25", "lvl_factor": "1.06", "won_points": "153", "event": "SSLT 5", "video": "PC", "rival": "Marv"}, {"result": "Victory", "won_rounds": 3, "played_rounds": 5, "raw_points": "972", "beating_factor": "0.60", "lvl_factor": "0.96", "won_points": "561", "event": "SSLT 7", "video": "PC", "rival": "Sigfrancis"}, {"result": "Defeat", "won_rounds": 2, "played_rounds": 5, "raw_points": "732", "beating_factor": "0.40", "lvl_factor": "0.95", "won_points": "277", "event": "SSLT 7", "video": "PC", "rival": "Sigfrancis"}, {"result": "Defeat", "won_rounds": 1, "played_rounds": 4, "raw_points": "492", "beating_factor": "0.25", "lvl_factor": "0.97", "won_points": "119", "event": "SSLT 7", "video": "PC", "rival": "Sigfrancis"}, {"result": "Defeat", "won_rounds": 2, "played_rounds": 5, "raw_points": "732", "beating_factor": "0.40", "lvl_factor": "0.97", "won_points": "285", "event": "SSLT 7", "video": "PC", "rival": "Eche"}, {"result": "Victory", "won_rounds": 3, "played_rounds": 3, "raw_points": "720", "beating_factor": "1.00", "lvl_factor": "0.99", "won_points": "712", "event": "SSLT 7", "video": "PC", "rival": "Eche"}, {"result": "Victory", "won_rounds": 3, "played_rounds": 3, "raw_points": "720", "beating_factor": "1.00", "lvl_factor": "0.98", "won_points": "704", "event": "SSLT 7", "video": "PC", "rival": "Eche"}, {"result": "Victory", "won_rounds": 3, "played_rounds": 4, "raw_points": "804", "beating_factor": "0.75", "lvl_factor": "0.97", "won_points": "587", "event": "SSLT 7", "video": "PC", "rival": "JaffarWolf"}, {"result": "Victory", "won_rounds": 3, "played_rounds": 3, "raw_points": "720", "beating_factor": "1.00", "lvl_factor": "0.97", "won_points": "695", "event": "SSLT 7", "video": "PC", "rival": "JaffarWolf"}, {"result": "Defeat", "won_rounds": 2, "played_rounds": 5, "raw_points": "648", "beating_factor": "0.40", "lvl_factor": "0.97", "won_points": "252", "event": "SSLT 7", "video": "PC", "rival": "DonMarlboro"}, {"result": "Victory", "won_rounds": 3, "played_rounds": 5, "raw_points": "972", "beating_factor": "0.60", "lvl_factor": "0.99", "won_points": "575", "event": "SSLT 7", "video": "PC", "rival": "DonMarlboro"}, {"result": "Defeat", "won_rounds": 0, "played_rounds": 3, "raw_points": "336", "beating_factor": "0.10", "lvl_factor": "0.98", "won_points": "33", "event": "SSLT 7", "video": "PC", "rival": "DonMarlboro"}], "player_stats": [{"rival": "zen-x", "played_battles": 7, "won_battles": 3, "lost_battles": 4, "draw_battles": 0, "win_rate": "43 %"}, {"rival": "JaffarWolf", "played_battles": 4, "won_battles": 4, "lost_battles": 0, "draw_battles": 0, "win_rate": "100 %"}, {"rival": "Maxxus", "played_battles": 2, "won_battles": 2, "lost_battles": 0, "draw_battles": 0, "win_rate": "100 %"}, {"rival": "Marv", "played_battles": 4, "won_battles": 1, "lost_battles": 3, "draw_battles": 0, "win_rate": "25 %"}, {"rival": "Sigfrancis", "played_battles": 3, "won_battles": 1, "lost_battles": 2, "draw_battles": 0, "win_rate": "33 %"}, {"rival": "Eche", "played_battles": 3, "won_battles": 2, "lost_battles": 1, "draw_battles": 0, "win_rate": "67 %"}, {"rival": "DonMarlboro", "played_battles": 3, "won_battles": 1, "lost_battles": 2, "draw_battles": 0, "win_rate": "33 %"}], "player": "Fire Red"}, {"played_battles": 26, "won_battles": 14, "lost_battles": 12, "draw_battles": 0, "win_rate": "53.85 %", "points_earned": "9628", "wlr": "1.17", "player_level": "11232", "battles_history": [{"result": "Victory", "won_rounds": 3, "played_rounds": 5, "raw_points": "972", "beating_factor": "0.60", "lvl_factor": "1.00", "won_points": "583", "event": "SSLT 1", "video": "PC", "rival": "wylde"}, {"result": "Defeat", "won_rounds": 0, "played_rounds": 3, "raw_points": "420", "beating_factor": "0.10", "lvl_factor": "0.81", "won_points": "34", "event": "SSLT 1", "video": "PC", "rival": "wylde"}, {"result": "Defeat", "won_rounds": 1, "played_rounds": 4, "raw_points": "576", "beating_factor": "0.25", "lvl_factor": "1.00", "won_points": "144", "event": "SSLT 1", "video": "PC", "rival": "wylde"}, {"result": "Victory", "won_rounds": 3, "played_rounds": 5, "raw_points": "888", "beating_factor": "0.60", "lvl_factor": "0.94", "won_points": "499", "event": "SSLT 1", "video": "PC", "rival": "Kovas"}, {"result": "Victory", "won_rounds": 3, "played_rounds": 5, "raw_points": "888", "beating_factor": "0.60", "lvl_factor": "0.91", "won_points": "482", "event": "SSLT 1", "video": "PC", "rival": "Kovas"}, {"result": "Victory", "won_rounds": 3, "played_rounds": 3, "raw_points": "720", "beating_factor": "1.00", "lvl_factor": "0.89", "won_points": "638", "event": "SSLT 1", "video": "PC", "rival": "Kovas"}, {"result": "Victory", "won_rounds": 3, "played_rounds": 4, "raw_points": "804", "beating_factor": "0.75", "lvl_factor": "1.03", "won_points": "622", "event": "SSLT 1", "video": "PC", "rival": "wylde"}, {"result": "Defeat", "won_rounds": 0, "played_rounds": 3, "raw_points": "336", "beating_factor": "0.10", "lvl_factor": "1.00", "won_points": "34", "event": "SSLT 1", "video": "PC", "rival": "wylde"}, {"result": "Defeat", "won_rounds": 0, "played_rounds": 3, "raw_points": "420", "beating_factor": "0.10", "lvl_factor": "1.02", "won_points": "43", "event": "SSLT 1", "video": "PC", "rival": "wylde"}, {"result": "Defeat", "won_rounds": 0, "played_rounds": 3, "raw_points": "420", "beating_factor": "0.10", "lvl_factor": "1.04", "won_points": "44", "event": "SSLT 1", "video": "PC", "rival": "wylde"}, {"result": "Victory", "won_rounds": 3, "played_rounds": 4, "raw_points": "888", "beating_factor": "0.75", "lvl_factor": "0.91", "won_points": "603", "event": "SSLT 3", "video": "PC", "rival": "Ubitreides"}, {"result": "Defeat", "won_rounds": 0, "played_rounds": 3, "raw_points": "252", "beating_factor": "0.10", "lvl_factor": "0.90", "won_points": "23", "event": "SSLT 3", "video": "PC", "rival": "Ubitreides"}, {"result": "Victory", "won_rounds": 3, "played_rounds": 4, "raw_points": "804", "beating_factor": "0.75", "lvl_factor": "1.00", "won_points": "603", "event": "SSLT 3", "video": "PC", "rival": "Ubitreides"}, {"result": "Defeat", "won_rounds": 2, "played_rounds": 5, "raw_points": "816", "beating_factor": "0.40", "lvl_factor": "1.02", "won_points": "334", "event": "SSLT 3", "video": "PC", "rival": "zen-x"}, {"result": "Defeat", "won_rounds": 0, "played_rounds": 3, "raw_points": "252", "beating_factor": "0.10", "lvl_factor": "1.05", "won_points": "26", "event": "SSLT 3", "video": "PC", "rival": "zen-x"}, {"result": "Victory", "won_rounds": 3, "played_rounds": 3, "raw_points": "720", "beating_factor": "1.00", "lvl_factor": "1.01", "won_points": "725", "event": "SSLT 3", "video": "PC", "rival": "Eche"}, {"result": "Victory", "won_rounds": 3, "played_rounds": 4, "raw_points": "804", "beating_factor": "0.75", "lvl_factor": "0.99", "won_points": "595", "event": "SSLT 3", "video": "PC", "rival": "Eche"}, {"result": "Victory", "won_rounds": 3, "played_rounds": 3, "raw_points": "720", "beating_factor": "1.00", "lvl_factor": "0.99", "won_points": "716", "event": "SSLT 3", "video": "PC", "rival": "JaffarWolf"}, {"result": "Victory", "won_rounds": 3, "played_rounds": 4, "raw_points": "720", "beating_factor": "0.75", "lvl_factor": "0.98", "won_points": "529", "event": "SSLT 3", "video": "PC", "rival": "JaffarWolf"}, {"result": "Victory", "won_rounds": 3, "played_rounds": 4, "raw_points": "804", "beating_factor": "0.75", "lvl_factor": "0.99", "won_points": "594", "event": "SSLT 3", "video": "PC", "rival": "zen-x"}, {"result": "Victory", "won_rounds": 3, "played_rounds": 4, "raw_points": "804", "beating_factor": "0.75", "lvl_factor": "0.97", "won_points": "585", "event": "SSLT 3", "video": "PC", "rival": "zen-x"}, {"result": "Defeat", "won_rounds": 0, "played_rounds": 3, "raw_points": "252", "beating_factor": "0.10", "lvl_factor": "0.96", "won_points": "24", "event": "SSLT 3", "video": "PC", "rival": "zen-x"}, {"result": "Victory", "won_rounds": 3, "played_rounds": 4, "raw_points": "804", "beating_factor": "0.75", "lvl_factor": "0.97", "won_points": "587", "event": "SSLT 3", "video": "PC", "rival": "zen-x"}, {"result": "Defeat", "won_rounds": 0, "played_rounds": 3, "raw_points": "420", "beating_factor": "0.10", "lvl_factor": "1.04", "won_points": "44", "event": "SSLT 3", "video": "PC", "rival": "wylde"}, {"result": "Defeat", "won_rounds": 2, "played_rounds": 5, "raw_points": "816", "beating_factor": "0.40", "lvl_factor": "1.05", "won_points": "342", "event": "SSLT 3", "video": "PC", "rival": "wylde"}, {"result": "Defeat", "won_rounds": 1, "played_rounds": 4, "raw_points": "660", "beating_factor": "0.25", "lvl_factor": "1.05", "won_points": "174", "event": "SSLT 3", "video": "PC", "rival": "wylde"}], "player_stats": [{"rival": "wylde", "played_battles": 10, "won_battles": 2, "lost_battles": 8, "draw_battles": 0, "win_rate": "20 %"}, {"rival": "Kovas", "played_battles": 3, "won_battles": 3, "lost_battles": 0, "draw_battles": 0, "win_rate": "100 %"}, {"rival": "Ubitreides", "played_battles": 3, "won_battles": 2, "lost_battles": 1, "draw_battles": 0, "win_rate": "67 %"}, {"rival": "zen-x", "played_battles": 6, "won_battles": 3, "lost_battles": 3, "draw_battles": 0, "win_rate": "50 %"}, {"rival": "Eche", "played_battles": 2, "won_battles": 2, "lost_battles": 0, "draw_battles": 0, "win_rate": "100 %"}, {"rival": "JaffarWolf", "played_battles": 2, "won_battles": 2, "lost_battles": 0, "draw_battles": 0, "win_rate": "100 %"}], "player": "raynarrok"}, {"played_battles": 25, "won_battles": 11, "lost_battles": 14, "draw_battles": 0, "win_rate": "44.00 %", "points_earned": "10487", "wlr": "0.79", "player_level": "8240", "battles_history": [{"result": "Defeat", "won_rounds": 1, "played_rounds": 4, "raw_points": "492", "beating_factor": "0.25", "lvl_factor": "1.00", "won_points": "123", "event": "SSLT 3", "video": "PC", "rival": "JaffarWolf"}, {"result": "Victory", "won_rounds": 3, "played_rounds": 4, "raw_points": "888", "beating_factor": "0.75", "lvl_factor": "1.19", "won_points": "792", "event": "SSLT 3", "video": "PC", "rival": "JaffarWolf"}, {"result": "Defeat", "won_rounds": 1, "played_rounds": 4, "raw_points": "576", "beating_factor": "0.25", "lvl_factor": "1.00", "won_points": "144", "event": "SSLT 3", "video": "PC", "rival": "JaffarWolf"}, {"result": "Defeat", "won_rounds": 2, "played_rounds": 5, "raw_points": "816", "beating_factor": "0.40", "lvl_factor": "1.00", "won_points": "326", "event": "SSLT 3", "video": "PC", "rival": "Eche"}, {"result": "Victory", "won_rounds": 3, "played_rounds": 4, "raw_points": "804", "beating_factor": "0.75", "lvl_factor": "1.05", "won_points": "632", "event": "SSLT 3", "video": "PC", "rival": "Eche"}, {"result": "Defeat", "won_rounds": 2, "played_rounds": 5, "raw_points": "732", "beating_factor": "0.40", "lvl_factor": "1.00", "won_points": "293", "event": "SSLT 3", "video": "PC", "rival": "Eche"}, {"result": "Victory", "won_rounds": 3, "played_rounds": 3, "raw_points": "720", "beating_factor": "1.00", "lvl_factor": "1.01", "won_points": "726", "event": "SSLT 7", "video": "PC", "rival": "Eche"}, {"result": "Defeat", "won_rounds": 2, "played_rounds": 5, "raw_points": "732", "beating_factor": "0.40", "lvl_factor": "0.98", "won_points": "288", "event": "SSLT 7", "video": "PC", "rival": "Eche"}, {"result": "Victory", "won_rounds": 3, "played_rounds": 3, "raw_points": "720", "beating_factor": "1.00", "lvl_factor": "1.00", "won_points": "723", "event": "SSLT 7", "video": "PC", "rival": "Eche"}, {"result": "Defeat", "won_rounds": 2, "played_rounds": 5, "raw_points": "900", "beating_factor": "0.40", "lvl_factor": "1.00", "won_points": "360", "event": "SSLT 7", "video": "PC", "rival": "Sigfrancis"}, {"result": "Defeat", "won_rounds": 0, "played_rounds": 3, "raw_points": "420", "beating_factor": "0.10", "lvl_factor": "1.02", "won_points": "43", "event": "SSLT 7", "video": "PC", "rival": "Sigfrancis"}, {"result": "Victory", "won_rounds": 3, "played_rounds": 5, "raw_points": "888", "beating_factor": "0.60", "lvl_factor": "1.08", "won_points": "578", "event": "SSLT 7", "video": "PC", "rival": "wylde"}, {"result": "Defeat", "won_rounds": 0, "played_rounds": 3, "raw_points": "252", "beating_factor": "0.10", "lvl_factor": "1.07", "won_points": "27", "event": "SSLT 7", "video": "PC", "rival": "wylde"}, {"result": "Victory", "won_rounds": 3, "played_rounds": 4, "raw_points": "888", "beating_factor": "0.75", "lvl_factor": "1.08", "won_points": "717", "event": "SSLT 7", "video": "PC", "rival": "wylde"}, {"result": "Victory", "won_rounds": 3, "played_rounds": 5, "raw_points": "972", "beating_factor": "0.60", "lvl_factor": "1.03", "won_points": "598", "event": "SSLT 7", "video": "PC", "rival": "Fire Red"}, {"result": "Defeat", "won_rounds": 2, "played_rounds": 5, "raw_points": "732", "beating_factor": "0.40", "lvl_factor": "1.01", "won_points": "297", "event": "SSLT 7", "video": "PC", "rival": "Fire Red"}, {"result": "Victory", "won_rounds": 3, "played_rounds": 3, "raw_points": "720", "beating_factor": "1.00", "lvl_factor": "1.02", "won_points": "737", "event": "SSLT 7", "video": "PC", "rival": "Fire Red"}, {"result": "Defeat", "won_rounds": 2, "played_rounds": 5, "raw_points": "816", "beating_factor": "0.40", "lvl_factor": "0.99", "won_points": "324", "event": "SSLT 7", "video": "PC", "rival": "Sigfrancis"}, {"result": "Victory", "won_rounds": 3, "played_rounds": 5, "raw_points": "972", "beating_factor": "0.60", "lvl_factor": "1.00", "won_points": "586", "event": "SSLT 7", "video": "PC", "rival": "Sigfrancis"}, {"result": "Victory", "won_rounds": 3, "played_rounds": 4, "raw_points": "804", "beating_factor": "0.75", "lvl_factor": "0.99", "won_points": "599", "event": "SSLT 7", "video": "PC", "rival": "Sigfrancis"}, {"result": "Defeat", "won_rounds": 2, "played_rounds": 5, "raw_points": "816", "beating_factor": "0.40", "lvl_factor": "0.98", "won_points": "321", "event": "SSLT 7", "video": "PC", "rival": "Sigfrancis"}, {"result": "Victory", "won_rounds": 3, "played_rounds": 5, "raw_points": "804", "beating_factor": "0.60", "lvl_factor": "0.99", "won_points": "479", "event": "SSLT 7", "video": "PC", "rival": "Sigfrancis"}, {"result": "Defeat", "won_rounds": 2, "played_rounds": 5, "raw_points": "732", "beating_factor": "0.40", "lvl_factor": "1.07", "won_points": "314", "event": "SSLT 7", "video": "PC", "rival": "Camus"}, {"result": "Defeat", "won_rounds": 2, "played_rounds": 5, "raw_points": "816", "beating_factor": "0.40", "lvl_factor": "1.08", "won_points": "352", "event": "SSLT 7", "video": "PC", "rival": "Camus"}, {"result": "Defeat", "won_rounds": 1, "played_rounds": 4, "raw_points": "408", "beating_factor": "0.25", "lvl_factor": "1.08", "won_points": "111", "event": "SSLT 7", "video": "PC", "rival": "Camus"}], "player_stats": [{"rival": "JaffarWolf", "played_battles": 3, "won_battles": 1, "lost_battles": 2, "draw_battles": 0, "win_rate": "33 %"}, {"rival": "Eche", "played_battles": 6, "won_battles": 3, "lost_battles": 3, "draw_battles": 0, "win_rate": "50 %"}, {"rival": "Sigfrancis", "played_battles": 7, "won_battles": 3, "lost_battles": 4, "draw_battles": 0, "win_rate": "43 %"}, {"rival": "wylde", "played_battles": 3, "won_battles": 2, "lost_battles": 1, "draw_battles": 0, "win_rate": "67 %"}, {"rival": "Fire Red", "played_battles": 3, "won_battles": 2, "lost_battles": 1, "draw_battles": 0, "win_rate": "67 %"}, {"rival": "Camus", "played_battles": 3, "won_battles": 0, "lost_battles": 3, "draw_battles": 0, "win_rate": "0 %"}], "player": "DonMarlboro"}, {"played_battles": 24, "won_battles": 11, "lost_battles": 13, "draw_battles": 0, "win_rate": "45.83 %", "points_earned": "9614", "wlr": "0.85", "player_level": "8135", "battles_history": [{"result": "Victory", "won_rounds": 3, "played_rounds": 5, "raw_points": "972", "beating_factor": "0.60", "lvl_factor": "1.00", "won_points": "583", "event": "SSLT 3", "video": "PC", "rival": "Sigfrancis"}, {"result": "Defeat", "won_rounds": 2, "played_rounds": 5, "raw_points": "816", "beating_factor": "0.40", "lvl_factor": "0.81", "won_points": "265", "event": "SSLT 3", "video": "PC", "rival": "Sigfrancis"}, {"result": "Victory", "won_rounds": 3, "played_rounds": 4, "raw_points": "888", "beating_factor": "0.75", "lvl_factor": "1.00", "won_points": "666", "event": "SSLT 3", "video": "PC", "rival": "Sigfrancis"}, {"result": "Victory", "won_rounds": 3, "played_rounds": 5, "raw_points": "1056", "beating_factor": "0.60", "lvl_factor": "0.98", "won_points": "618", "event": "SSLT 3", "video": "PC", "rival": "raynarrok"}, {"result": "Victory", "won_rounds": 3, "played_rounds": 3, "raw_points": "720", "beating_factor": "1.00", "lvl_factor": "0.95", "won_points": "686", "event": "SSLT 3", "video": "PC", "rival": "raynarrok"}, {"result": "Defeat", "won_rounds": 2, "played_rounds": 5, "raw_points": "816", "beating_factor": "0.40", "lvl_factor": "1.00", "won_points": "326", "event": "SSLT 3", "video": "PC", "rival": "wylde"}, {"result": "Defeat", "won_rounds": 2, "played_rounds": 5, "raw_points": "900", "beating_factor": "0.40", "lvl_factor": "1.03", "won_points": "370", "event": "SSLT 3", "video": "PC", "rival": "wylde"}, {"result": "Defeat", "won_rounds": 2, "played_rounds": 5, "raw_points": "732", "beating_factor": "0.40", "lvl_factor": "1.05", "won_points": "307", "event": "SSLT 3", "video": "PC", "rival": "wylde"}, {"result": "Defeat", "won_rounds": 1, "played_rounds": 4, "raw_points": "576", "beating_factor": "0.25", "lvl_factor": "1.01", "won_points": "146", "event": "SSLT 3", "video": "PC", "rival": "raynarrok"}, {"result": "Defeat", "won_rounds": 1, "played_rounds": 4, "raw_points": "576", "beating_factor": "0.25", "lvl_factor": "1.03", "won_points": "148", "event": "SSLT 3", "video": "PC", "rival": "raynarrok"}, {"result": "Victory", "won_rounds": 3, "played_rounds": 3, "raw_points": "720", "beating_factor": "1.00", "lvl_factor": "1.04", "won_points": "750", "event": "SSLT 3", "video": "PC", "rival": "raynarrok"}, {"result": "Defeat", "won_rounds": 1, "played_rounds": 4, "raw_points": "576", "beating_factor": "0.25", "lvl_factor": "1.03", "won_points": "148", "event": "SSLT 3", "video": "PC", "rival": "raynarrok"}, {"result": "Victory", "won_rounds": 3, "played_rounds": 5, "raw_points": "888", "beating_factor": "0.60", "lvl_factor": "0.92", "won_points": "491", "event": "SSLT 5", "video": "PC", "rival": "Fire Red"}, {"result": "Victory", "won_rounds": 3, "played_rounds": 3, "raw_points": "720", "beating_factor": "1.00", "lvl_factor": "0.91", "won_points": "657", "event": "SSLT 5", "video": "PC", "rival": "Fire Red"}, {"result": "Victory", "won_rounds": 3, "played_rounds": 5, "raw_points": "972", "beating_factor": "0.60", "lvl_factor": "1.09", "won_points": "638", "event": "SSLT 5", "video": "PC", "rival": "Maxxus"}, {"result": "Victory", "won_rounds": 3, "played_rounds": 5, "raw_points": "972", "beating_factor": "0.60", "lvl_factor": "1.03", "won_points": "598", "event": "SSLT 5", "video": "PC", "rival": "Maxxus"}, {"result": "Defeat", "won_rounds": 1, "played_rounds": 4, "raw_points": "576", "beating_factor": "0.25", "lvl_factor": "1.08", "won_points": "156", "event": "SSLT 5", "video": "PC", "rival": "Marv"}, {"result": "Defeat", "won_rounds": 0, "played_rounds": 3, "raw_points": "252", "beating_factor": "0.10", "lvl_factor": "1.09", "won_points": "27", "event": "SSLT 5", "video": "PC", "rival": "Marv"}, {"result": "Defeat", "won_rounds": 0, "played_rounds": 3, "raw_points": "420", "beating_factor": "0.10", "lvl_factor": "1.09", "won_points": "46", "event": "SSLT 5", "video": "PC", "rival": "Marv"}, {"result": "Victory", "won_rounds": 3, "played_rounds": 5, "raw_points": "972", "beating_factor": "0.60", "lvl_factor": "1.04", "won_points": "605", "event": "SSLT 5", "video": "PC", "rival": "Fire Red"}, {"result": "Defeat", "won_rounds": 0, "played_rounds": 3, "raw_points": "168", "beating_factor": "0.10", "lvl_factor": "1.01", "won_points": "17", "event": "SSLT 5", "video": "PC", "rival": "Fire Red"}, {"result": "Defeat", "won_rounds": 2, "played_rounds": 5, "raw_points": "816", "beating_factor": "0.40", "lvl_factor": "1.03", "won_points": "336", "event": "SSLT 5", "video": "PC", "rival": "Fire Red"}, {"result": "Victory", "won_rounds": 3, "played_rounds": 4, "raw_points": "804", "beating_factor": "0.75", "lvl_factor": "1.04", "won_points": "627", "event": "SSLT 5", "video": "PC", "rival": "Fire Red"}, {"result": "Defeat", "won_rounds": 2, "played_rounds": 5, "raw_points": "984", "beating_factor": "0.40", "lvl_factor": "1.02", "won_points": "403", "event": "SSLT 5", "video": "PC", "rival": "Fire Red"}], "player_stats": [{"rival": "Sigfrancis", "played_battles": 3, "won_battles": 2, "lost_battles": 1, "draw_battles": 0, "win_rate": "67 %"}, {"rival": "raynarrok", "played_battles": 6, "won_battles": 3, "lost_battles": 3, "draw_battles": 0, "win_rate": "50 %"}, {"rival": "wylde", "played_battles": 3, "won_battles": 0, "lost_battles": 3, "draw_battles": 0, "win_rate": "0 %"}, {"rival": "Fire Red", "played_battles": 7, "won_battles": 4, "lost_battles": 3, "draw_battles": 0, "win_rate": "57 %"}, {"rival": "Maxxus", "played_battles": 2, "won_battles": 2, "lost_battles": 0, "draw_battles": 0, "win_rate": "100 %"}, {"rival": "Marv", "played_battles": 3, "won_battles": 0, "lost_battles": 3, "draw_battles": 0, "win_rate": "0 %"}], "player": "zen-x"}, {"played_battles": 19, "won_battles": 8, "lost_battles": 11, "draw_battles": 0, "win_rate": "42.11 %", "points_earned": "7520", "wlr": "0.73", "player_level": "5469", "battles_history": [{"result": "Defeat", "won_rounds": 2, "played_rounds": 5, "raw_points": "816", "beating_factor": "0.40", "lvl_factor": "1.00", "won_points": "326", "event": "SSLT 3", "video": "PC", "rival": "zen-x"}, {"result": "Victory", "won_rounds": 3, "played_rounds": 5, "raw_points": "972", "beating_factor": "0.60", "lvl_factor": "1.19", "won_points": "694", "event": "SSLT 3", "video": "PC", "rival": "zen-x"}, {"result": "Defeat", "won_rounds": 1, "played_rounds": 4, "raw_points": "408", "beating_factor": "0.25", "lvl_factor": "1.00", "won_points": "102", "event": "SSLT 3", "video": "PC", "rival": "zen-x"}, {"result": "Victory", "won_rounds": 3, "played_rounds": 3, "raw_points": "720", "beating_factor": "1.00", "lvl_factor": "1.00", "won_points": "720", "event": "SSLT 3", "video": "PC", "rival": "Ubitreides"}, {"result": "Defeat", "won_rounds": 2, "played_rounds": 5, "raw_points": "900", "beating_factor": "0.40", "lvl_factor": "0.95", "won_points": "343", "event": "SSLT 3", "video": "PC", "rival": "Ubitreides"}, {"result": "Defeat", "won_rounds": 2, "played_rounds": 5, "raw_points": "900", "beating_factor": "0.40", "lvl_factor": "1.00", "won_points": "360", "event": "SSLT 3", "video": "PC", "rival": "Ubitreides"}, {"result": "Defeat", "won_rounds": 2, "played_rounds": 5, "raw_points": "984", "beating_factor": "0.40", "lvl_factor": "1.04", "won_points": "409", "event": "SSLT 7", "video": "PC", "rival": "Fire Red"}, {"result": "Victory", "won_rounds": 3, "played_rounds": 5, "raw_points": "804", "beating_factor": "0.60", "lvl_factor": "1.05", "won_points": "508", "event": "SSLT 7", "video": "PC", "rival": "Fire Red"}, {"result": "Victory", "won_rounds": 3, "played_rounds": 4, "raw_points": "804", "beating_factor": "0.75", "lvl_factor": "1.03", "won_points": "621", "event": "SSLT 7", "video": "PC", "rival": "Fire Red"}, {"result": "Victory", "won_rounds": 3, "played_rounds": 5, "raw_points": "888", "beating_factor": "0.60", "lvl_factor": "1.00", "won_points": "533", "event": "SSLT 7", "video": "PC", "rival": "DonMarlboro"}, {"result": "Victory", "won_rounds": 3, "played_rounds": 3, "raw_points": "720", "beating_factor": "1.00", "lvl_factor": "0.98", "won_points": "706", "event": "SSLT 7", "video": "PC", "rival": "DonMarlboro"}, {"result": "Defeat", "won_rounds": 0, "played_rounds": 3, "raw_points": "252", "beating_factor": "0.10", "lvl_factor": "1.05", "won_points": "26", "event": "SSLT 7", "video": "PC", "rival": "Camus"}, {"result": "Defeat", "won_rounds": 0, "played_rounds": 3, "raw_points": "252", "beating_factor": "0.10", "lvl_factor": "1.06", "won_points": "27", "event": "SSLT 7", "video": "PC", "rival": "Camus"}, {"result": "Defeat", "won_rounds": 1, "played_rounds": 4, "raw_points": "576", "beating_factor": "0.25", "lvl_factor": "1.07", "won_points": "155", "event": "SSLT 7", "video": "PC", "rival": "Camus"}, {"result": "Victory", "won_rounds": 3, "played_rounds": 5, "raw_points": "972", "beating_factor": "0.60", "lvl_factor": "1.01", "won_points": "588", "event": "SSLT 7", "video": "PC", "rival": "DonMarlboro"}, {"result": "Defeat", "won_rounds": 2, "played_rounds": 5, "raw_points": "900", "beating_factor": "0.40", "lvl_factor": "1.00", "won_points": "358", "event": "SSLT 7", "video": "PC", "rival": "DonMarlboro"}, {"result": "Defeat", "won_rounds": 1, "played_rounds": 4, "raw_points": "492", "beating_factor": "0.25", "lvl_factor": "1.01", "won_points": "124", "event": "SSLT 7", "video": "PC", "rival": "DonMarlboro"}, {"result": "Victory", "won_rounds": 3, "played_rounds": 5, "raw_points": "972", "beating_factor": "0.60", "lvl_factor": "1.02", "won_points": "593", "event": "SSLT 7", "video": "PC", "rival": "DonMarlboro"}, {"result": "Defeat", "won_rounds": 2, "played_rounds": 5, "raw_points": "816", "beating_factor": "0.40", "lvl_factor": "1.01", "won_points": "328", "event": "SSLT 7", "video": "PC", "rival": "DonMarlboro"}], "player_stats": [{"rival": "zen-x", "played_battles": 3, "won_battles": 1, "lost_battles": 2, "draw_battles": 0, "win_rate": "33 %"}, {"rival": "Ubitreides", "played_battles": 3, "won_battles": 1, "lost_battles": 2, "draw_battles": 0, "win_rate": "33 %"}, {"rival": "Fire Red", "played_battles": 3, "won_battles": 2, "lost_battles": 1, "draw_battles": 0, "win_rate": "67 %"}, {"rival": "DonMarlboro", "played_battles": 7, "won_battles": 4, "lost_battles": 3, "draw_battles": 0, "win_rate": "57 %"}, {"rival": "Camus", "played_battles": 3, "won_battles": 0, "lost_battles": 3, "draw_battles": 0, "win_rate": "0 %"}], "player": "Sigfrancis"}, {"played_battles": 23, "won_battles": 8, "lost_battles": 15, "draw_battles": 0, "win_rate": "34.78 %", "points_earned": "6268", "wlr": "0.53", "player_level": "3343", "battles_history": [{"result": "Victory", "won_rounds": 3, "played_rounds": 4, "raw_points": "804", "beating_factor": "0.75", "lvl_factor": "1.00", "won_points": "603", "event": "SSLT 3", "video": "PC", "rival": "DonMarlboro"}, {"result": "Defeat", "won_rounds": 1, "played_rounds": 4, "raw_points": "492", "beating_factor": "0.25", "lvl_factor": "0.81", "won_points": "100", "event": "SSLT 3", "video": "PC", "rival": "DonMarlboro"}, {"result": "Victory", "won_rounds": 3, "played_rounds": 4, "raw_points": "720", "beating_factor": "0.75", "lvl_factor": "1.00", "won_points": "540", "event": "SSLT 3", "video": "PC", "rival": "DonMarlboro"}, {"result": "Defeat", "won_rounds": 1, "played_rounds": 4, "raw_points": "492", "beating_factor": "0.25", "lvl_factor": "1.02", "won_points": "125", "event": "SSLT 3", "video": "PC", "rival": "wylde"}, {"result": "Defeat", "won_rounds": 1, "played_rounds": 4, "raw_points": "576", "beating_factor": "0.25", "lvl_factor": "1.05", "won_points": "152", "event": "SSLT 3", "video": "PC", "rival": "wylde"}, {"result": "Victory", "won_rounds": 3, "played_rounds": 4, "raw_points": "804", "beating_factor": "0.75", "lvl_factor": "1.02", "won_points": "614", "event": "SSLT 3", "video": "PC", "rival": "Ubitreides"}, {"result": "Defeat", "won_rounds": 2, "played_rounds": 5, "raw_points": "900", "beating_factor": "0.40", "lvl_factor": "0.99", "won_points": "355", "event": "SSLT 3", "video": "PC", "rival": "Ubitreides"}, {"result": "Victory", "won_rounds": 3, "played_rounds": 5, "raw_points": "972", "beating_factor": "0.60", "lvl_factor": "1.01", "won_points": "591", "event": "SSLT 3", "video": "PC", "rival": "Ubitreides"}, {"result": "Defeat", "won_rounds": 0, "played_rounds": 3, "raw_points": "336", "beating_factor": "0.10", "lvl_factor": "1.01", "won_points": "34", "event": "SSLT 3", "video": "PC", "rival": "raynarrok"}, {"result": "Defeat", "won_rounds": 1, "played_rounds": 4, "raw_points": "576", "beating_factor": "0.25", "lvl_factor": "1.02", "won_points": "147", "event": "SSLT 3", "video": "PC", "rival": "raynarrok"}, {"result": "Victory", "won_rounds": 3, "played_rounds": 4, "raw_points": "888", "beating_factor": "0.75", "lvl_factor": "0.92", "won_points": "616", "event": "SSLT 5", "video": "PC", "rival": "Kovas"}, {"result": "Victory", "won_rounds": 3, "played_rounds": 3, "raw_points": "720", "beating_factor": "1.00", "lvl_factor": "0.91", "won_points": "658", "event": "SSLT 5", "video": "PC", "rival": "Kovas"}, {"result": "Defeat", "won_rounds": 1, "played_rounds": 4, "raw_points": "492", "beating_factor": "0.25", "lvl_factor": "1.09", "won_points": "135", "event": "SSLT 5", "video": "PC", "rival": "Marv"}, {"result": "Defeat", "won_rounds": 0, "played_rounds": 3, "raw_points": "84", "beating_factor": "0.10", "lvl_factor": "1.10", "won_points": "9", "event": "SSLT 5", "video": "PC", "rival": "Marv"}, {"result": "Defeat", "won_rounds": 0, "played_rounds": 3, "raw_points": "336", "beating_factor": "0.10", "lvl_factor": "0.92", "won_points": "31", "event": "SSLT 5", "video": "PC", "rival": "Fire Red"}, {"result": "Defeat", "won_rounds": 1, "played_rounds": 4, "raw_points": "492", "beating_factor": "0.25", "lvl_factor": "0.99", "won_points": "121", "event": "SSLT 5", "video": "PC", "rival": "Fire Red"}, {"result": "Victory", "won_rounds": 3, "played_rounds": 4, "raw_points": "804", "beating_factor": "0.75", "lvl_factor": "0.97", "won_points": "587", "event": "SSLT 7", "video": "PC", "rival": "Kovas"}, {"result": "Defeat", "won_rounds": 0, "played_rounds": 3, "raw_points": "336", "beating_factor": "0.10", "lvl_factor": "0.96", "won_points": "32", "event": "SSLT 7", "video": "PC", "rival": "Kovas"}, {"result": "Victory", "won_rounds": 3, "played_rounds": 5, "raw_points": "972", "beating_factor": "0.60", "lvl_factor": "0.98", "won_points": "570", "event": "SSLT 7", "video": "PC", "rival": "Kovas"}, {"result": "Defeat", "won_rounds": 0, "played_rounds": 3, "raw_points": "252", "beating_factor": "0.10", "lvl_factor": "1.05", "won_points": "26", "event": "SSLT 7", "video": "PC", "rival": "Camus"}, {"result": "Defeat", "won_rounds": 0, "played_rounds": 3, "raw_points": "168", "beating_factor": "0.10", "lvl_factor": "1.07", "won_points": "18", "event": "SSLT 7", "video": "PC", "rival": "Camus"}, {"result": "Defeat", "won_rounds": 1, "played_rounds": 4, "raw_points": "660", "beating_factor": "0.25", "lvl_factor": "1.03", "won_points": "169", "event": "SSLT 7", "video": "PC", "rival": "Fire Red"}, {"result": "Defeat", "won_rounds": 0, "played_rounds": 3, "raw_points": "336", "beating_factor": "0.10", "lvl_factor": "1.03", "won_points": "35", "event": "SSLT 7", "video": "PC", "rival": "Fire Red"}], "player_stats": [{"rival": "DonMarlboro", "played_battles": 3, "won_battles": 2, "lost_battles": 1, "draw_battles": 0, "win_rate": "67 %"}, {"rival": "wylde", "played_battles": 2, "won_battles": 0, "lost_battles": 2, "draw_battles": 0, "win_rate": "0 %"}, {"rival": "Ubitreides", "played_battles": 3, "won_battles": 2, "lost_battles": 1, "draw_battles": 0, "win_rate": "67 %"}, {"rival": "raynarrok", "played_battles": 2, "won_battles": 0, "lost_battles": 2, "draw_battles": 0, "win_rate": "0 %"}, {"rival": "Kovas", "played_battles": 5, "won_battles": 4, "lost_battles": 1, "draw_battles": 0, "win_rate": "80 %"}, {"rival": "Marv", "played_battles": 2, "won_battles": 0, "lost_battles": 2, "draw_battles": 0, "win_rate": "0 %"}, {"rival": "Fire Red", "played_battles": 4, "won_battles": 0, "lost_battles": 4, "draw_battles": 0, "win_rate": "0 %"}, {"rival": "Camus", "played_battles": 2, "won_battles": 0, "lost_battles": 2, "draw_battles": 0, "win_rate": "0 %"}], "player": "JaffarWolf"}, {"played_battles": 9, "won_battles": 4, "lost_battles": 5, "draw_battles": 0, "win_rate": "44.44 %", "points_earned": "3560", "wlr": "0.80", "player_level": "2848", "battles_history": [{"result": "Victory", "won_rounds": 3, "played_rounds": 3, "raw_points": "720", "beating_factor": "1.00", "lvl_factor": "1.00", "won_points": "720", "event": "SSLT 5", "video": "PC", "rival": "Never"}, {"result": "Victory", "won_rounds": 3, "played_rounds": 3, "raw_points": "720", "beating_factor": "1.00", "lvl_factor": "0.81", "won_points": "584", "event": "SSLT 5", "video": "PC", "rival": "Never"}, {"result": "Defeat", "won_rounds": 2, "played_rounds": 5, "raw_points": "648", "beating_factor": "0.40", "lvl_factor": "0.91", "won_points": "235", "event": "SSLT 5", "video": "PC", "rival": "zen-x"}, {"result": "Defeat", "won_rounds": 2, "played_rounds": 5, "raw_points": "732", "beating_factor": "0.40", "lvl_factor": "0.97", "won_points": "285", "event": "SSLT 5", "video": "PC", "rival": "zen-x"}, {"result": "Defeat", "won_rounds": 0, "played_rounds": 3, "raw_points": "420", "beating_factor": "0.10", "lvl_factor": "0.94", "won_points": "40", "event": "SSLT 5", "video": "PC", "rival": "Kovas"}, {"result": "Victory", "won_rounds": 3, "played_rounds": 4, "raw_points": "804", "beating_factor": "0.75", "lvl_factor": "0.98", "won_points": "588", "event": "SSLT 5", "video": "PC", "rival": "Kovas"}, {"result": "Victory", "won_rounds": 3, "played_rounds": 5, "raw_points": "972", "beating_factor": "0.60", "lvl_factor": "0.95", "won_points": "556", "event": "SSLT 5", "video": "PC", "rival": "Kovas"}, {"result": "Defeat", "won_rounds": 2, "played_rounds": 5, "raw_points": "732", "beating_factor": "0.40", "lvl_factor": "0.99", "won_points": "289", "event": "SSLT 5", "video": "PC", "rival": "Fire Red"}, {"result": "Defeat", "won_rounds": 2, "played_rounds": 5, "raw_points": "648", "beating_factor": "0.40", "lvl_factor": "1.02", "won_points": "264", "event": "SSLT 5", "video": "PC", "rival": "Fire Red"}], "player_stats": [{"rival": "Never", "played_battles": 2, "won_battles": 2, "lost_battles": 0, "draw_battles": 0, "win_rate": "100 %"}, {"rival": "zen-x", "played_battles": 2, "won_battles": 0, "lost_battles": 2, "draw_battles": 0, "win_rate": "0 %"}, {"rival": "Kovas", "played_battles": 3, "won_battles": 2, "lost_battles": 1, "draw_battles": 0, "win_rate": "67 %"}, {"rival": "Fire Red", "played_battles": 2, "won_battles": 0, "lost_battles": 2, "draw_battles": 0, "win_rate": "0 %"}], "player": "Maxxus"}, {"played_battles": 9, "won_battles": 4, "lost_battles": 5, "draw_battles": 0, "win_rate": "44.44 %", "points_earned": "3324", "wlr": "0.80", "player_level": "2659", "battles_history": [{"result": "Defeat", "won_rounds": 1, "played_rounds": 4, "raw_points": "492", "beating_factor": "0.25", "lvl_factor": "1.09", "won_points": "135", "event": "SSLT 3", "video": "PC", "rival": "raynarrok"}, {"result": "Victory", "won_rounds": 3, "played_rounds": 3, "raw_points": "720", "beating_factor": "1.00", "lvl_factor": "1.10", "won_points": "794", "event": "SSLT 3", "video": "PC", "rival": "raynarrok"}, {"result": "Defeat", "won_rounds": 1, "played_rounds": 4, "raw_points": "576", "beating_factor": "0.25", "lvl_factor": "1.00", "won_points": "144", "event": "SSLT 3", "video": "PC", "rival": "raynarrok"}, {"result": "Defeat", "won_rounds": 0, "played_rounds": 3, "raw_points": "252", "beating_factor": "0.10", "lvl_factor": "1.00", "won_points": "25", "event": "SSLT 3", "video": "PC", "rival": "Sigfrancis"}, {"result": "Victory", "won_rounds": 3, "played_rounds": 5, "raw_points": "888", "beating_factor": "0.60", "lvl_factor": "1.05", "won_points": "558", "event": "SSLT 3", "video": "PC", "rival": "Sigfrancis"}, {"result": "Victory", "won_rounds": 3, "played_rounds": 5, "raw_points": "972", "beating_factor": "0.60", "lvl_factor": "1.00", "won_points": "583", "event": "SSLT 3", "video": "PC", "rival": "Sigfrancis"}, {"result": "Defeat", "won_rounds": 1, "played_rounds": 4, "raw_points": "492", "beating_factor": "0.25", "lvl_factor": "0.98", "won_points": "121", "event": "SSLT 3", "video": "PC", "rival": "JaffarWolf"}, {"result": "Victory", "won_rounds": 3, "played_rounds": 5, "raw_points": "1056", "beating_factor": "0.60", "lvl_factor": "1.01", "won_points": "642", "event": "SSLT 3", "video": "PC", "rival": "JaffarWolf"}, {"result": "Defeat", "won_rounds": 2, "played_rounds": 5, "raw_points": "816", "beating_factor": "0.40", "lvl_factor": "0.99", "won_points": "322", "event": "SSLT 3", "video": "PC", "rival": "JaffarWolf"}], "player_stats": [{"rival": "raynarrok", "played_battles": 3, "won_battles": 1, "lost_battles": 2, "draw_battles": 0, "win_rate": "33 %"}, {"rival": "Sigfrancis", "played_battles": 3, "won_battles": 2, "lost_battles": 1, "draw_battles": 0, "win_rate": "67 %"}, {"rival": "JaffarWolf", "played_battles": 3, "won_battles": 1, "lost_battles": 2, "draw_battles": 0, "win_rate": "33 %"}], "player": "Ubitreides"}, {"played_battles": 14, "won_battles": 5, "lost_battles": 9, "draw_battles": 0, "win_rate": "35.71 %", "points_earned": "3930", "wlr": "0.56", "player_level": "2184", "battles_history": [{"result": "Victory", "won_rounds": 3, "played_rounds": 5, "raw_points": "804", "beating_factor": "0.60", "lvl_factor": "1.15", "won_points": "555", "event": "SSLT 3", "video": "PC", "rival": "wylde"}, {"result": "Defeat", "won_rounds": 2, "played_rounds": 5, "raw_points": "900", "beating_factor": "0.40", "lvl_factor": "0.95", "won_points": "341", "event": "SSLT 3", "video": "PC", "rival": "wylde"}, {"result": "Defeat", "won_rounds": 2, "played_rounds": 5, "raw_points": "816", "beating_factor": "0.40", "lvl_factor": "1.05", "won_points": "342", "event": "SSLT 3", "video": "PC", "rival": "wylde"}, {"result": "Victory", "won_rounds": 3, "played_rounds": 5, "raw_points": "972", "beating_factor": "0.60", "lvl_factor": "1.00", "won_points": "583", "event": "SSLT 3", "video": "PC", "rival": "DonMarlboro"}, {"result": "Defeat", "won_rounds": 1, "played_rounds": 4, "raw_points": "492", "beating_factor": "0.25", "lvl_factor": "0.95", "won_points": "117", "event": "SSLT 3", "video": "PC", "rival": "DonMarlboro"}, {"result": "Victory", "won_rounds": 3, "played_rounds": 5, "raw_points": "972", "beating_factor": "0.60", "lvl_factor": "1.00", "won_points": "583", "event": "SSLT 3", "video": "PC", "rival": "DonMarlboro"}, {"result": "Defeat", "won_rounds": 0, "played_rounds": 3, "raw_points": "336", "beating_factor": "0.10", "lvl_factor": "0.99", "won_points": "33", "event": "SSLT 3", "video": "PC", "rival": "raynarrok"}, {"result": "Defeat", "won_rounds": 1, "played_rounds": 4, "raw_points": "492", "beating_factor": "0.25", "lvl_factor": "1.01", "won_points": "125", "event": "SSLT 3", "video": "PC", "rival": "raynarrok"}, {"result": "Defeat", "won_rounds": 0, "played_rounds": 3, "raw_points": "168", "beating_factor": "0.10", "lvl_factor": "0.99", "won_points": "17", "event": "SSLT 7", "video": "PC", "rival": "DonMarlboro"}, {"result": "Victory", "won_rounds": 3, "played_rounds": 5, "raw_points": "972", "beating_factor": "0.60", "lvl_factor": "1.02", "won_points": "594", "event": "SSLT 7", "video": "PC", "rival": "DonMarlboro"}, {"result": "Defeat", "won_rounds": 0, "played_rounds": 3, "raw_points": "336", "beating_factor": "0.10", "lvl_factor": "1.00", "won_points": "33", "event": "SSLT 7", "video": "PC", "rival": "DonMarlboro"}, {"result": "Victory", "won_rounds": 3, "played_rounds": 5, "raw_points": "888", "beating_factor": "0.60", "lvl_factor": "1.03", "won_points": "547", "event": "SSLT 7", "video": "PC", "rival": "Fire Red"}, {"result": "Defeat", "won_rounds": 0, "played_rounds": 3, "raw_points": "336", "beating_factor": "0.10", "lvl_factor": "1.01", "won_points": "34", "event": "SSLT 7", "video": "PC", "rival": "Fire Red"}, {"result": "Defeat", "won_rounds": 0, "played_rounds": 3, "raw_points": "252", "beating_factor": "0.10", "lvl_factor": "1.02", "won_points": "26", "event": "SSLT 7", "video": "PC", "rival": "Fire Red"}], "player_stats": [{"rival": "wylde", "played_battles": 3, "won_battles": 1, "lost_battles": 2, "draw_battles": 0, "win_rate": "33 %"}, {"rival": "DonMarlboro", "played_battles": 6, "won_battles": 3, "lost_battles": 3, "draw_battles": 0, "win_rate": "50 %"}, {"rival": "raynarrok", "played_battles": 2, "won_battles": 0, "lost_battles": 2, "draw_battles": 0, "win_rate": "0 %"}, {"rival": "Fire Red", "played_battles": 3, "won_battles": 1, "lost_battles": 2, "draw_battles": 0, "win_rate": "33 %"}], "player": "Eche"}, {"played_battles": 18, "won_battles": 4, "lost_battles": 14, "draw_battles": 0, "win_rate": "22.22 %", "points_earned": "4926", "wlr": "0.29", "player_level": "1408", "battles_history": [{"result": "Defeat", "won_rounds": 1, "played_rounds": 4, "raw_points": "492", "beating_factor": "0.25", "lvl_factor": "1.13", "won_points": "139", "event": "SSLT 1", "video": "PC", "rival": "wylde"}, {"result": "Defeat", "won_rounds": 0, "played_rounds": 3, "raw_points": "252", "beating_factor": "0.10", "lvl_factor": "1.14", "won_points": "29", "event": "SSLT 1", "video": "PC", "rival": "wylde"}, {"result": "Defeat", "won_rounds": 0, "played_rounds": 3, "raw_points": "336", "beating_factor": "0.10", "lvl_factor": "1.15", "won_points": "39", "event": "SSLT 1", "video": "PC", "rival": "wylde"}, {"result": "Defeat", "won_rounds": 2, "played_rounds": 5, "raw_points": "816", "beating_factor": "0.40", "lvl_factor": "1.06", "won_points": "347", "event": "SSLT 1", "video": "PC", "rival": "raynarrok"}, {"result": "Defeat", "won_rounds": 2, "played_rounds": 5, "raw_points": "816", "beating_factor": "0.40", "lvl_factor": "1.09", "won_points": "357", "event": "SSLT 1", "video": "PC", "rival": "raynarrok"}, {"result": "Defeat", "won_rounds": 0, "played_rounds": 3, "raw_points": "504", "beating_factor": "0.10", "lvl_factor": "1.11", "won_points": "56", "event": "SSLT 1", "video": "PC", "rival": "raynarrok"}, {"result": "Defeat", "won_rounds": 1, "played_rounds": 4, "raw_points": "492", "beating_factor": "0.25", "lvl_factor": "1.08", "won_points": "132", "event": "SSLT 5", "video": "PC", "rival": "JaffarWolf"}, {"result": "Defeat", "won_rounds": 0, "played_rounds": 3, "raw_points": "252", "beating_factor": "0.10", "lvl_factor": "1.09", "won_points": "27", "event": "SSLT 5", "video": "PC", "rival": "JaffarWolf"}, {"result": "Victory", "won_rounds": 3, "played_rounds": 4, "raw_points": "804", "beating_factor": "0.75", "lvl_factor": "1.00", "won_points": "603", "event": "SSLT 5", "video": "PC", "rival": "Megarl"}, {"result": "Victory", "won_rounds": 3, "played_rounds": 3, "raw_points": "720", "beating_factor": "1.00", "lvl_factor": "0.98", "won_points": "705", "event": "SSLT 5", "video": "PC", "rival": "Megarl"}, {"result": "Victory", "won_rounds": 3, "played_rounds": 3, "raw_points": "720", "beating_factor": "1.00", "lvl_factor": "1.06", "won_points": "761", "event": "SSLT 5", "video": "PC", "rival": "Maxxus"}, {"result": "Defeat", "won_rounds": 1, "played_rounds": 4, "raw_points": "492", "beating_factor": "0.25", "lvl_factor": "1.02", "won_points": "126", "event": "SSLT 5", "video": "PC", "rival": "Maxxus"}, {"result": "Defeat", "won_rounds": 2, "played_rounds": 5, "raw_points": "900", "beating_factor": "0.40", "lvl_factor": "1.05", "won_points": "377", "event": "SSLT 5", "video": "PC", "rival": "Maxxus"}, {"result": "Defeat", "won_rounds": 1, "played_rounds": 4, "raw_points": "492", "beating_factor": "0.25", "lvl_factor": "1.03", "won_points": "126", "event": "SSLT 7", "video": "PC", "rival": "JaffarWolf"}, {"result": "Victory", "won_rounds": 3, "played_rounds": 3, "raw_points": "720", "beating_factor": "1.00", "lvl_factor": "1.04", "won_points": "747", "event": "SSLT 7", "video": "PC", "rival": "JaffarWolf"}, {"result": "Defeat", "won_rounds": 2, "played_rounds": 5, "raw_points": "732", "beating_factor": "0.40", "lvl_factor": "1.02", "won_points": "300", "event": "SSLT 7", "video": "PC", "rival": "JaffarWolf"}, {"result": "Defeat", "won_rounds": 0, "played_rounds": 3, "raw_points": "252", "beating_factor": "0.10", "lvl_factor": "1.10", "won_points": "28", "event": "SSLT 7", "video": "PC", "rival": "wylde"}, {"result": "Defeat", "won_rounds": 0, "played_rounds": 3, "raw_points": "252", "beating_factor": "0.10", "lvl_factor": "1.11", "won_points": "28", "event": "SSLT 7", "video": "PC", "rival": "wylde"}], "player_stats": [{"rival": "wylde", "played_battles": 5, "won_battles": 0, "lost_battles": 5, "draw_battles": 0, "win_rate": "0 %"}, {"rival": "raynarrok", "played_battles": 3, "won_battles": 0, "lost_battles": 3, "draw_battles": 0, "win_rate": "0 %"}, {"rival": "JaffarWolf", "played_battles": 5, "won_battles": 1, "lost_battles": 4, "draw_battles": 0, "win_rate": "20 %"}, {"rival": "Megarl", "played_battles": 2, "won_battles": 2, "lost_battles": 0, "draw_battles": 0, "win_rate": "100 %"}, {"rival": "Maxxus", "played_battles": 3, "won_battles": 1, "lost_battles": 2, "draw_battles": 0, "win_rate": "33 %"}], "player": "Kovas"}, {"played_battles": 4, "won_battles": 0, "lost_battles": 4, "draw_battles": 0, "win_rate": "0.00 %", "points_earned": "287", "wlr": "0.25", "player_level": "72", "battles_history": [{"result": "Defeat", "won_rounds": 1, "played_rounds": 4, "raw_points": "324", "beating_factor": "0.25", "lvl_factor": "1.00", "won_points": "81", "event": "SSLT 5", "video": "PC", "rival": "Marv"}, {"result": "Defeat", "won_rounds": 0, "played_rounds": 3, "raw_points": "336", "beating_factor": "0.10", "lvl_factor": "1.19", "won_points": "40", "event": "SSLT 5", "video": "PC", "rival": "Marv"}, {"result": "Defeat", "won_rounds": 1, "played_rounds": 4, "raw_points": "492", "beating_factor": "0.25", "lvl_factor": "1.00", "won_points": "123", "event": "SSLT 5", "video": "PC", "rival": "Kovas"}, {"result": "Defeat", "won_rounds": 0, "played_rounds": 3, "raw_points": "420", "beating_factor": "0.10", "lvl_factor": "1.02", "won_points": "43", "event": "SSLT 5", "video": "PC", "rival": "Kovas"}], "player_stats": [{"rival": "Marv", "played_battles": 2, "won_battles": 0, "lost_battles": 2, "draw_battles": 0, "win_rate": "0 %"}, {"rival": "Kovas", "played_battles": 2, "won_battles": 0, "lost_battles": 2, "draw_battles": 0, "win_rate": "0 %"}], "player": "Megarl"}, {"played_battles": 2, "won_battles": 0, "lost_battles": 2, "draw_battles": 0, "win_rate": "0.00 %", "points_earned": "35", "wlr": "0.50", "player_level": "18", "battles_history": [{"result": "Defeat", "won_rounds": 0, "played_rounds": 3, "raw_points": "252", "beating_factor": "0.10", "lvl_factor": "1.00", "won_points": "25", "event": "SSLT 5", "video": "PC", "rival": "Maxxus"}, {"result": "Defeat", "won_rounds": 0, "played_rounds": 3, "raw_points": "84", "beating_factor": "0.10", "lvl_factor": "1.19", "won_points": "10", "event": "SSLT 5", "video": "PC", "rival": "Maxxus"}], "player_stats": [{"rival": "Maxxus", "played_battles": 2, "won_battles": 0, "lost_battles": 2, "draw_battles": 0, "win_rate": "0 %"}], "player": "Never"}]